{
  "batch_id": "largemouth_v3_gold_batch_1",
  "generated_at": "2026-04-14T00:53:28.803Z",
  "archive_bundle_generated_at": "2026-04-04T01:40:13.529Z",
  "scenario_count": 10,
  "score_keys": [
    "seasonal_fit",
    "daily_fit",
    "water_column_fit",
    "archetype_fit",
    "color_fit",
    "top3_variety",
    "boundedness"
  ],
  "scenarios": [
    {
      "scenario_id": "lmb_florida_jan_pond_postfront",
      "label": "Florida pond largemouth, winter post-front control day",
      "priority": "core",
      "species": "largemouth_bass",
      "context": "freshwater_lake_pond",
      "water_clarity": "stained",
      "state_code": "FL",
      "timezone": "America/New_York",
      "local_date": "2025-01-23",
      "latitude": 28.0614,
      "longitude": -82.3026,
      "expectation": {
        "seasonal_story": "Winter Florida bass should stay in a controlled bottom-to-lower-mid lane, not a surface lane.",
        "primary_lanes": [
          "football_jig",
          "texas_rigged_soft_plastic_craw",
          "suspending_jerkbait"
        ],
        "acceptable_secondary_lanes": [
          "compact_flipping_jig",
          "shaky_head_worm",
          "paddle_tail_swimbait"
        ],
        "disallowed_lanes": [
          "hollow_body_frog",
          "walking_topwater",
          "mouse_fly"
        ],
        "expected_color_lanes": [
          "natural",
          "natural",
          "dark"
        ],
        "notes": [
          "Daily warming may raise pace slightly, but should not create a drastic surface jump."
        ]
      },
      "engine_run_status": "complete",
      "archived_env_summary": [
        "Region: florida",
        "Archive weather timezone: America/New_York",
        "Noon air temp: 47.4 F",
        "Noon pressure: 1025.4 mb",
        "Noon cloud cover: 100%",
        "Daily high/low: 55.8 / 39 F",
        "Daily wind max: 10.3 mph",
        "Daily precip: 0 in",
        "Moon phase: Waning Crescent",
        "Sunrise/sunset: 07:18 / 18:03"
      ],
      "actual_output": {
        "top_1_lure": {
          "id": "football_jig",
          "display_name": "Football Jig",
          "score": 6.68,
          "tactical_lane": "bottom_contact",
          "color_theme": "bright",
          "color_recommendations": [
            "white/chartreuse",
            "chartreuse",
            "firetiger"
          ]
        },
        "top_3_lures": [
          {
            "id": "football_jig",
            "display_name": "Football Jig",
            "score": 6.68,
            "tactical_lane": "bottom_contact",
            "color_theme": "bright",
            "color_recommendations": [
              "white/chartreuse",
              "chartreuse",
              "firetiger"
            ]
          },
          {
            "id": "shaky_head_worm",
            "display_name": "Shaky-Head Worm",
            "score": 3.52,
            "tactical_lane": "bottom_contact",
            "color_theme": "bright",
            "color_recommendations": [
              "white/chartreuse",
              "chartreuse",
              "firetiger"
            ]
          },
          {
            "id": "compact_flipping_jig",
            "display_name": "Compact Flipping Jig",
            "score": 5.27,
            "tactical_lane": "cover_weedless",
            "color_theme": "bright",
            "color_recommendations": [
              "white/chartreuse",
              "chartreuse",
              "firetiger"
            ]
          }
        ],
        "top_1_fly": {
          "id": "rabbit_strip_leech",
          "display_name": "Rabbit-Strip Leech",
          "score": 5.91,
          "tactical_lane": "fly_bottom",
          "color_theme": "bright",
          "color_recommendations": [
            "white/chartreuse",
            "chartreuse",
            "firetiger"
          ]
        },
        "top_3_flies": [
          {
            "id": "rabbit_strip_leech",
            "display_name": "Rabbit-Strip Leech",
            "score": 5.91,
            "tactical_lane": "fly_bottom",
            "color_theme": "bright",
            "color_recommendations": [
              "white/chartreuse",
              "chartreuse",
              "firetiger"
            ]
          },
          {
            "id": "sculpin_streamer",
            "display_name": "Sculpin Streamer",
            "score": 5.91,
            "tactical_lane": "fly_bottom",
            "color_theme": "bright",
            "color_recommendations": [
              "white/chartreuse",
              "chartreuse",
              "firetiger"
            ]
          },
          {
            "id": "woolly_bugger",
            "display_name": "Woolly Bugger",
            "score": 5.91,
            "tactical_lane": "fly_bottom",
            "color_theme": "bright",
            "color_recommendations": [
              "white/chartreuse",
              "chartreuse",
              "firetiger"
            ]
          }
        ],
        "color_notes": [
          "Color of day: Bright Colors",
          "Football Jig: bright -> white/chartreuse, chartreuse, firetiger",
          "Shaky-Head Worm: bright -> white/chartreuse, chartreuse, firetiger",
          "Compact Flipping Jig: bright -> white/chartreuse, chartreuse, firetiger",
          "Rabbit-Strip Leech: bright -> white/chartreuse, chartreuse, firetiger",
          "Sculpin Streamer: bright -> white/chartreuse, chartreuse, firetiger",
          "Woolly Bugger: bright -> white/chartreuse, chartreuse, firetiger"
        ],
        "daily_profile_notes": [
          "Daily posture: slightly_suppressed (3.3/10)",
          "Presentation presence today: bold",
          "Resolved profile: typical_column=mid_low, likely_column_today=low, seasonal_location=mid_deep, posture=slightly_suppressed, presentation=bold",
          "Guardrails: surface_allowed=true, suppress_true_topwater=false, suppress_fast_presentations=true, high_visibility_needed=true, column_shift_half_steps=1",
          "Variables considered: temperature_metabolic_context, temperature_trend, temperature_shock, pressure_regime, wind_condition, light_cloud_condition, precipitation_disruption",
          "Variables triggered: temperature_metabolic_context, wind_condition, light_cloud_condition, precipitation_disruption",
          "Daily note: Cold-limited metabolism suppresses fish posture and tightens the bite lane.",
          "Daily note: Moderate chop supports a slightly more open lake posture.",
          "Daily note: Heavy overcast supports a more open feeding posture.",
          "Daily note: Stained water supports a balanced presentation with some extra presence."
        ]
      },
      "review": {
        "precheck_flags": [
          "TOP1_PRIMARY_HIT",
          "TOP3_PRIMARY_PRESENT",
          "NO_DISALLOWED_PRESENT",
          "TOP_COLOR_MATCH:bright,bright"
        ],
        "top_1_verdict": "",
        "top_3_verdict": "",
        "scores": {
          "seasonal_fit": null,
          "daily_fit": null,
          "water_column_fit": null,
          "archetype_fit": null,
          "color_fit": null,
          "top3_variety": null,
          "boundedness": null
        },
        "failure_clusters": [],
        "notes": ""
      }
    },
    {
      "scenario_id": "lmb_florida_mar_lake_prespawn",
      "label": "Florida natural lake largemouth, prespawn opening window",
      "priority": "core",
      "species": "largemouth_bass",
      "context": "freshwater_lake_pond",
      "water_clarity": "clear",
      "state_code": "FL",
      "timezone": "America/New_York",
      "local_date": "2025-03-20",
      "latitude": 28.5383,
      "longitude": -81.3792,
      "expectation": {
        "seasonal_story": "Prespawn Florida largemouth should allow moving bait and jerkbait lanes without abandoning bottom-control options.",
        "primary_lanes": [
          "suspending_jerkbait",
          "paddle_tail_swimbait",
          "compact_flipping_jig"
        ],
        "acceptable_secondary_lanes": [
          "spinnerbait",
          "texas_rigged_stick_worm",
          "swim_jig"
        ],
        "disallowed_lanes": [
          "blade_bait",
          "mouse_fly"
        ],
        "expected_color_lanes": [
          "natural",
          "natural",
          "natural"
        ]
      },
      "engine_run_status": "complete",
      "archived_env_summary": [
        "Region: florida",
        "Archive weather timezone: America/New_York",
        "Noon air temp: 76.7 F",
        "Noon pressure: 1017.1 mb",
        "Noon cloud cover: 0%",
        "Daily high/low: 82.6 / 55.8 F",
        "Daily wind max: 18.2 mph",
        "Daily precip: 0.003937007874015749 in",
        "Moon phase: Waning Gibbous",
        "Sunrise/sunset: 07:27 / 19:38"
      ],
      "actual_output": {
        "top_1_lure": {
          "id": "paddle_tail_swimbait",
          "display_name": "Paddle-Tail Swimbait",
          "score": 6.57,
          "tactical_lane": "horizontal_search",
          "color_theme": "natural",
          "color_recommendations": [
            "green pumpkin",
            "olive",
            "smoke"
          ]
        },
        "top_3_lures": [
          {
            "id": "paddle_tail_swimbait",
            "display_name": "Paddle-Tail Swimbait",
            "score": 6.57,
            "tactical_lane": "horizontal_search",
            "color_theme": "natural",
            "color_recommendations": [
              "green pumpkin",
              "olive",
              "smoke"
            ]
          },
          {
            "id": "suspending_jerkbait",
            "display_name": "Suspending Jerkbait",
            "score": 6.55,
            "tactical_lane": "reaction_mid_column",
            "color_theme": "natural",
            "color_recommendations": [
              "green pumpkin",
              "olive",
              "smoke"
            ]
          },
          {
            "id": "soft_jerkbait",
            "display_name": "Soft Plastic Jerkbait",
            "score": 6.18,
            "tactical_lane": "horizontal_search",
            "color_theme": "natural",
            "color_recommendations": [
              "green pumpkin",
              "olive",
              "smoke"
            ]
          }
        ],
        "top_1_fly": {
          "id": "woolly_bugger",
          "display_name": "Woolly Bugger",
          "score": 5.7,
          "tactical_lane": "fly_bottom",
          "color_theme": "natural",
          "color_recommendations": [
            "green pumpkin",
            "olive",
            "smoke"
          ]
        },
        "top_3_flies": [
          {
            "id": "woolly_bugger",
            "display_name": "Woolly Bugger",
            "score": 5.7,
            "tactical_lane": "fly_bottom",
            "color_theme": "natural",
            "color_recommendations": [
              "green pumpkin",
              "olive",
              "smoke"
            ]
          },
          {
            "id": "rabbit_strip_leech",
            "display_name": "Rabbit-Strip Leech",
            "score": 4.6,
            "tactical_lane": "fly_bottom",
            "color_theme": "natural",
            "color_recommendations": [
              "green pumpkin",
              "olive",
              "smoke"
            ]
          },
          {
            "id": "crawfish_streamer",
            "display_name": "Crawfish Streamer",
            "score": 4.1,
            "tactical_lane": "fly_bottom",
            "color_theme": "natural",
            "color_recommendations": [
              "green pumpkin",
              "olive",
              "smoke"
            ]
          }
        ],
        "color_notes": [
          "Color of day: Natural Colors",
          "Paddle-Tail Swimbait: natural -> green pumpkin, olive, smoke",
          "Suspending Jerkbait: natural -> green pumpkin, olive, smoke",
          "Soft Plastic Jerkbait: natural -> green pumpkin, olive, smoke",
          "Woolly Bugger: natural -> green pumpkin, olive, smoke",
          "Rabbit-Strip Leech: natural -> green pumpkin, olive, smoke",
          "Crawfish Streamer: natural -> green pumpkin, olive, smoke"
        ],
        "daily_profile_notes": [
          "Daily posture: neutral (6.4/10)",
          "Presentation presence today: subtle",
          "Resolved profile: typical_column=high, likely_column_today=high, seasonal_location=shallow, posture=neutral, presentation=subtle",
          "Guardrails: surface_allowed=false, suppress_true_topwater=true, suppress_fast_presentations=false, high_visibility_needed=false, column_shift_half_steps=0",
          "Variables considered: temperature_metabolic_context, temperature_trend, temperature_shock, pressure_regime, wind_condition, light_cloud_condition, precipitation_disruption",
          "Variables triggered: temperature_metabolic_context, temperature_trend, wind_condition, light_cloud_condition, precipitation_disruption",
          "Daily note: Neutral temperature metabolism keeps the day open to the normal seasonal pattern.",
          "Daily note: A warming trend nudges fish into a slightly more willing posture.",
          "Daily note: Moderate chop supports a slightly more open lake posture.",
          "Daily note: Bright light trims daily willingness without fully shutting the day down.",
          "Daily note: Clear water favors a cleaner, subtler presentation."
        ]
      },
      "review": {
        "precheck_flags": [
          "TOP1_PRIMARY_HIT",
          "TOP3_PRIMARY_PRESENT",
          "NO_DISALLOWED_PRESENT",
          "TOP_COLOR_MATCH:natural,natural"
        ],
        "top_1_verdict": "",
        "top_3_verdict": "",
        "scores": {
          "seasonal_fit": null,
          "daily_fit": null,
          "water_column_fit": null,
          "archetype_fit": null,
          "color_fit": null,
          "top3_variety": null,
          "boundedness": null
        },
        "failure_clusters": [],
        "notes": ""
      }
    },
    {
      "scenario_id": "lmb_texas_feb_reservoir_wind",
      "label": "Texas reservoir largemouth, late-winter windy baitfish day",
      "priority": "core",
      "species": "largemouth_bass",
      "context": "freshwater_lake_pond",
      "water_clarity": "stained",
      "state_code": "TX",
      "timezone": "America/Chicago",
      "local_date": "2025-02-19",
      "latitude": 31.101,
      "longitude": -95.566,
      "expectation": {
        "seasonal_story": "Southern reservoir bass can lean baitfish and wind-reactive, but truly harsh late-winter cold snaps can still collapse the day back toward a football jig while keeping one moving-lane backup alive.",
        "primary_lanes": [
          "football_jig",
          "spinnerbait",
          "bladed_jig",
          "suspending_jerkbait"
        ],
        "acceptable_secondary_lanes": [
          "paddle_tail_swimbait",
          "texas_rigged_soft_plastic_craw",
          "swim_jig"
        ],
        "disallowed_lanes": [
          "hollow_body_frog",
          "popper_fly"
        ],
        "expected_color_lanes": [
          "natural",
          "bright",
          "dark"
        ]
      },
      "engine_run_status": "complete",
      "archived_env_summary": [
        "Region: south_central",
        "Archive weather timezone: America/Chicago",
        "Noon air temp: 34.1 F",
        "Noon pressure: 1031.2 mb",
        "Noon cloud cover: 100%",
        "Daily high/low: 37.3 / 20 F",
        "Daily wind max: 12.9 mph",
        "Daily precip: 0 in",
        "Moon phase: Waning Gibbous",
        "Sunrise/sunset: 06:57 / 18:14"
      ],
      "actual_output": {
        "top_1_lure": {
          "id": "football_jig",
          "display_name": "Football Jig",
          "score": 8.58,
          "tactical_lane": "bottom_contact",
          "color_theme": "bright",
          "color_recommendations": [
            "white/chartreuse",
            "chartreuse",
            "firetiger"
          ]
        },
        "top_3_lures": [
          {
            "id": "football_jig",
            "display_name": "Football Jig",
            "score": 8.58,
            "tactical_lane": "bottom_contact",
            "color_theme": "bright",
            "color_recommendations": [
              "white/chartreuse",
              "chartreuse",
              "firetiger"
            ]
          },
          {
            "id": "texas_rigged_soft_plastic_craw",
            "display_name": "Texas-Rigged Soft-Plastic Craw",
            "score": 4.09,
            "tactical_lane": "cover_weedless",
            "color_theme": "bright",
            "color_recommendations": [
              "white/chartreuse",
              "chartreuse",
              "firetiger"
            ]
          },
          {
            "id": "bladed_jig",
            "display_name": "Bladed Jig",
            "score": 2.58,
            "tactical_lane": "horizontal_search",
            "color_theme": "bright",
            "color_recommendations": [
              "white/chartreuse",
              "chartreuse",
              "firetiger"
            ]
          }
        ],
        "top_1_fly": {
          "id": "rabbit_strip_leech",
          "display_name": "Rabbit-Strip Leech",
          "score": 7.51,
          "tactical_lane": "fly_bottom",
          "color_theme": "bright",
          "color_recommendations": [
            "white/chartreuse",
            "chartreuse",
            "firetiger"
          ]
        },
        "top_3_flies": [
          {
            "id": "rabbit_strip_leech",
            "display_name": "Rabbit-Strip Leech",
            "score": 7.51,
            "tactical_lane": "fly_bottom",
            "color_theme": "bright",
            "color_recommendations": [
              "white/chartreuse",
              "chartreuse",
              "firetiger"
            ]
          },
          {
            "id": "sculpin_streamer",
            "display_name": "Sculpin Streamer",
            "score": 7.51,
            "tactical_lane": "fly_bottom",
            "color_theme": "bright",
            "color_recommendations": [
              "white/chartreuse",
              "chartreuse",
              "firetiger"
            ]
          },
          {
            "id": "woolly_bugger",
            "display_name": "Woolly Bugger",
            "score": 7.51,
            "tactical_lane": "fly_bottom",
            "color_theme": "bright",
            "color_recommendations": [
              "white/chartreuse",
              "chartreuse",
              "firetiger"
            ]
          }
        ],
        "color_notes": [
          "Color of day: Bright Colors",
          "Football Jig: bright -> white/chartreuse, chartreuse, firetiger",
          "Texas-Rigged Soft-Plastic Craw: bright -> white/chartreuse, chartreuse, firetiger",
          "Bladed Jig: bright -> white/chartreuse, chartreuse, firetiger",
          "Rabbit-Strip Leech: bright -> white/chartreuse, chartreuse, firetiger",
          "Sculpin Streamer: bright -> white/chartreuse, chartreuse, firetiger",
          "Woolly Bugger: bright -> white/chartreuse, chartreuse, firetiger"
        ],
        "daily_profile_notes": [
          "Daily posture: suppressed (2.4/10)",
          "Presentation presence today: bold",
          "Resolved profile: typical_column=mid, likely_column_today=low, seasonal_location=mid, posture=suppressed, presentation=bold",
          "Guardrails: surface_allowed=false, suppress_true_topwater=true, suppress_fast_presentations=true, high_visibility_needed=true, column_shift_half_steps=2",
          "Variables considered: temperature_metabolic_context, temperature_trend, temperature_shock, pressure_regime, wind_condition, light_cloud_condition, precipitation_disruption",
          "Variables triggered: temperature_metabolic_context, temperature_trend, wind_condition, light_cloud_condition, precipitation_disruption",
          "Daily note: Cold-limited metabolism suppresses fish posture and tightens the bite lane.",
          "Daily note: A cooling trend tightens fish and reduces daily willingness.",
          "Daily note: Moderate chop supports a slightly more open lake posture.",
          "Daily note: Low light opens the daily posture and supports more willingness.",
          "Daily note: Recent rain keeps the lake bite a little more controlled and selective.",
          "Daily note: Stained water supports a balanced presentation with some extra presence."
        ]
      },
      "review": {
        "precheck_flags": [
          "TOP1_PRIMARY_HIT",
          "TOP3_PRIMARY_PRESENT",
          "NO_DISALLOWED_PRESENT",
          "TOP_COLOR_MATCH:bright,bright"
        ],
        "top_1_verdict": "",
        "top_3_verdict": "",
        "scores": {
          "seasonal_fit": null,
          "daily_fit": null,
          "water_column_fit": null,
          "archetype_fit": null,
          "color_fit": null,
          "top3_variety": null,
          "boundedness": null
        },
        "failure_clusters": [],
        "notes": ""
      }
    },
    {
      "scenario_id": "lmb_georgia_apr_highland_clear",
      "label": "Highland reservoir largemouth, clear-water spring setup",
      "priority": "core",
      "species": "largemouth_bass",
      "context": "freshwater_lake_pond",
      "water_clarity": "clear",
      "state_code": "GA",
      "timezone": "America/New_York",
      "local_date": "2025-04-16",
      "latitude": 34.579,
      "longitude": -83.543,
      "expectation": {
        "seasonal_story": "Clear highland largemouth in spring can still tighten into target cover and shallow finesse on cold, bright days even when baitfish lanes remain seasonally relevant.",
        "primary_lanes": [
          "wacky_rigged_stick_worm",
          "compact_flipping_jig",
          "paddle_tail_swimbait"
        ],
        "acceptable_secondary_lanes": [
          "swim_jig",
          "soft_jerkbait",
          "clouser_minnow",
          "woolly_bugger"
        ],
        "disallowed_lanes": [
          "hollow_body_frog"
        ],
        "expected_color_lanes": [
          "natural",
          "natural",
          "natural"
        ]
      },
      "engine_run_status": "complete",
      "archived_env_summary": [
        "Region: south_central",
        "Archive weather timezone: America/New_York",
        "Noon air temp: 59.7 F",
        "Noon pressure: 1020.2 mb",
        "Noon cloud cover: 0%",
        "Daily high/low: 65.5 / 41.3 F",
        "Daily wind max: 10.1 mph",
        "Daily precip: 0 in",
        "Moon phase: Waning Gibbous",
        "Sunrise/sunset: 06:59 / 20:08"
      ],
      "actual_output": {
        "top_1_lure": {
          "id": "wacky_rigged_stick_worm",
          "display_name": "Wacky-Rigged Stick Worm",
          "score": 7.26,
          "tactical_lane": "finesse_subtle",
          "color_theme": "natural",
          "color_recommendations": [
            "green pumpkin",
            "olive",
            "smoke"
          ]
        },
        "top_3_lures": [
          {
            "id": "wacky_rigged_stick_worm",
            "display_name": "Wacky-Rigged Stick Worm",
            "score": 7.26,
            "tactical_lane": "finesse_subtle",
            "color_theme": "natural",
            "color_recommendations": [
              "green pumpkin",
              "olive",
              "smoke"
            ]
          },
          {
            "id": "compact_flipping_jig",
            "display_name": "Compact Flipping Jig",
            "score": 4.59,
            "tactical_lane": "cover_weedless",
            "color_theme": "natural",
            "color_recommendations": [
              "green pumpkin",
              "olive",
              "smoke"
            ]
          },
          {
            "id": "paddle_tail_swimbait",
            "display_name": "Paddle-Tail Swimbait",
            "score": 2.42,
            "tactical_lane": "horizontal_search",
            "color_theme": "natural",
            "color_recommendations": [
              "green pumpkin",
              "olive",
              "smoke"
            ]
          }
        ],
        "top_1_fly": {
          "id": "woolly_bugger",
          "display_name": "Woolly Bugger",
          "score": 7.73,
          "tactical_lane": "fly_bottom",
          "color_theme": "natural",
          "color_recommendations": [
            "green pumpkin",
            "olive",
            "smoke"
          ]
        },
        "top_3_flies": [
          {
            "id": "woolly_bugger",
            "display_name": "Woolly Bugger",
            "score": 7.73,
            "tactical_lane": "fly_bottom",
            "color_theme": "natural",
            "color_recommendations": [
              "green pumpkin",
              "olive",
              "smoke"
            ]
          },
          {
            "id": "rabbit_strip_leech",
            "display_name": "Rabbit-Strip Leech",
            "score": 6.13,
            "tactical_lane": "fly_bottom",
            "color_theme": "natural",
            "color_recommendations": [
              "green pumpkin",
              "olive",
              "smoke"
            ]
          },
          {
            "id": "clouser_minnow",
            "display_name": "Clouser Minnow",
            "score": 1.47,
            "tactical_lane": "fly_baitfish",
            "color_theme": "natural",
            "color_recommendations": [
              "green pumpkin",
              "olive",
              "smoke"
            ]
          }
        ],
        "color_notes": [
          "Color of day: Natural Colors",
          "Wacky-Rigged Stick Worm: natural -> green pumpkin, olive, smoke",
          "Compact Flipping Jig: natural -> green pumpkin, olive, smoke",
          "Paddle-Tail Swimbait: natural -> green pumpkin, olive, smoke",
          "Woolly Bugger: natural -> green pumpkin, olive, smoke",
          "Rabbit-Strip Leech: natural -> green pumpkin, olive, smoke",
          "Clouser Minnow: natural -> green pumpkin, olive, smoke"
        ],
        "daily_profile_notes": [
          "Daily posture: suppressed (2.4/10)",
          "Presentation presence today: subtle",
          "Resolved profile: typical_column=top, likely_column_today=high, seasonal_location=shallow, posture=suppressed, presentation=subtle",
          "Guardrails: surface_allowed=false, suppress_true_topwater=true, suppress_fast_presentations=true, high_visibility_needed=false, column_shift_half_steps=2",
          "Variables considered: temperature_metabolic_context, temperature_trend, temperature_shock, pressure_regime, wind_condition, light_cloud_condition, precipitation_disruption",
          "Variables triggered: temperature_metabolic_context, wind_condition, light_cloud_condition, precipitation_disruption",
          "Daily note: Cold-limited metabolism suppresses fish posture and tightens the bite lane.",
          "Daily note: Moderate chop supports a slightly more open lake posture.",
          "Daily note: Bright light trims daily willingness without fully shutting the day down.",
          "Daily note: Clear water favors a cleaner, subtler presentation."
        ]
      },
      "review": {
        "precheck_flags": [
          "TOP1_PRIMARY_HIT",
          "TOP3_PRIMARY_PRESENT",
          "NO_DISALLOWED_PRESENT",
          "TOP_COLOR_MATCH:natural,natural"
        ],
        "top_1_verdict": "",
        "top_3_verdict": "",
        "scores": {
          "seasonal_fit": null,
          "daily_fit": null,
          "water_column_fit": null,
          "archetype_fit": null,
          "color_fit": null,
          "top3_variety": null,
          "boundedness": null
        },
        "failure_clusters": [],
        "notes": ""
      }
    },
    {
      "scenario_id": "lmb_alabama_may_river_current",
      "label": "Alabama river largemouth, spring current seam pattern",
      "priority": "core",
      "species": "largemouth_bass",
      "context": "freshwater_river",
      "water_clarity": "stained",
      "state_code": "AL",
      "timezone": "America/Chicago",
      "local_date": "2025-05-12",
      "latitude": 34.8,
      "longitude": -87.67,
      "expectation": {
        "seasonal_story": "River largemouth should still reflect bass current positioning instead of generic lake behavior.",
        "primary_lanes": [
          "spinnerbait",
          "swim_jig",
          "soft_jerkbait"
        ],
        "acceptable_secondary_lanes": [
          "compact_flipping_jig",
          "paddle_tail_swimbait",
          "game_changer"
        ],
        "disallowed_lanes": [
          "hollow_body_frog"
        ],
        "expected_color_lanes": [
          "natural",
          "bright",
          "natural"
        ]
      },
      "engine_run_status": "complete",
      "archived_env_summary": [
        "Region: south_central",
        "Archive weather timezone: America/Chicago",
        "Noon air temp: 73.3 F",
        "Noon pressure: 1012.4 mb",
        "Noon cloud cover: 90%",
        "Daily high/low: 74.2 / 61.7 F",
        "Daily wind max: 11.1 mph",
        "Daily precip: 0.6614173228346457 in",
        "Moon phase: Full Moon",
        "Sunrise/sunset: 05:47 / 19:46"
      ],
      "actual_output": {
        "top_1_lure": {
          "id": "soft_jerkbait",
          "display_name": "Soft Plastic Jerkbait",
          "score": 4.87,
          "tactical_lane": "horizontal_search",
          "color_theme": "dark",
          "color_recommendations": [
            "black",
            "black/blue",
            "black/purple"
          ]
        },
        "top_3_lures": [
          {
            "id": "soft_jerkbait",
            "display_name": "Soft Plastic Jerkbait",
            "score": 4.87,
            "tactical_lane": "horizontal_search",
            "color_theme": "dark",
            "color_recommendations": [
              "black",
              "black/blue",
              "black/purple"
            ]
          },
          {
            "id": "compact_flipping_jig",
            "display_name": "Compact Flipping Jig",
            "score": 3.38,
            "tactical_lane": "cover_weedless",
            "color_theme": "dark",
            "color_recommendations": [
              "black",
              "black/blue",
              "black/purple"
            ]
          },
          {
            "id": "texas_rigged_soft_plastic_craw",
            "display_name": "Texas-Rigged Soft-Plastic Craw",
            "score": 2.18,
            "tactical_lane": "cover_weedless",
            "color_theme": "dark",
            "color_recommendations": [
              "black",
              "black/blue",
              "black/purple"
            ]
          }
        ],
        "top_1_fly": {
          "id": "rabbit_strip_leech",
          "display_name": "Rabbit-Strip Leech",
          "score": 3.66,
          "tactical_lane": "fly_bottom",
          "color_theme": "dark",
          "color_recommendations": [
            "black",
            "black/blue",
            "black/purple"
          ]
        },
        "top_3_flies": [
          {
            "id": "rabbit_strip_leech",
            "display_name": "Rabbit-Strip Leech",
            "score": 3.66,
            "tactical_lane": "fly_bottom",
            "color_theme": "dark",
            "color_recommendations": [
              "black",
              "black/blue",
              "black/purple"
            ]
          },
          {
            "id": "game_changer",
            "display_name": "Game Changer",
            "score": 3.5,
            "tactical_lane": "fly_baitfish",
            "color_theme": "dark",
            "color_recommendations": [
              "black",
              "black/blue",
              "black/purple"
            ]
          },
          {
            "id": "deceiver",
            "display_name": "Deceiver",
            "score": 3.4,
            "tactical_lane": "fly_baitfish",
            "color_theme": "dark",
            "color_recommendations": [
              "black",
              "black/blue",
              "black/purple"
            ]
          }
        ],
        "color_notes": [
          "Color of day: Dark Colors",
          "Soft Plastic Jerkbait: dark -> black, black/blue, black/purple",
          "Compact Flipping Jig: dark -> black, black/blue, black/purple",
          "Texas-Rigged Soft-Plastic Craw: dark -> black, black/blue, black/purple",
          "Rabbit-Strip Leech: dark -> black, black/blue, black/purple",
          "Game Changer: dark -> black, black/blue, black/purple",
          "Deceiver: dark -> black, black/blue, black/purple"
        ],
        "daily_profile_notes": [
          "Daily posture: slightly_suppressed (4.4/10)",
          "Presentation presence today: balanced",
          "Resolved profile: typical_column=top, likely_column_today=high_top, seasonal_location=shallow, posture=slightly_suppressed, presentation=balanced",
          "Guardrails: surface_allowed=true, suppress_true_topwater=false, suppress_fast_presentations=true, high_visibility_needed=false, column_shift_half_steps=1",
          "Variables considered: temperature_metabolic_context, temperature_trend, temperature_shock, pressure_regime, wind_condition, light_cloud_condition, runoff_flow_disruption",
          "Variables triggered: temperature_metabolic_context, temperature_trend, wind_condition, light_cloud_condition, runoff_flow_disruption",
          "Daily note: Neutral temperature metabolism keeps the day open to the normal seasonal pattern.",
          "Daily note: A warming trend nudges fish into a slightly more willing posture.",
          "Daily note: Elevated flow suppresses posture and tightens fish to safer holding lanes.",
          "Daily note: Stained water supports a balanced presentation with some extra presence."
        ]
      },
      "review": {
        "precheck_flags": [
          "TOP1_PRIMARY_HIT",
          "TOP3_PRIMARY_PRESENT",
          "NO_DISALLOWED_PRESENT",
          "TOP_COLOR_MATCH:dark,dark"
        ],
        "top_1_verdict": "",
        "top_3_verdict": "",
        "scores": {
          "seasonal_fit": null,
          "daily_fit": null,
          "water_column_fit": null,
          "archetype_fit": null,
          "color_fit": null,
          "top3_variety": null,
          "boundedness": null
        },
        "failure_clusters": [],
        "notes": ""
      }
    },
    {
      "scenario_id": "lmb_mississippi_jun_backwater_dirty",
      "label": "Mississippi backwater largemouth, warm stained summer cover day",
      "priority": "secondary",
      "species": "largemouth_bass",
      "context": "freshwater_river",
      "water_clarity": "dirty",
      "state_code": "TN",
      "timezone": "America/Chicago",
      "local_date": "2025-06-18",
      "latitude": 35.143,
      "longitude": -90.052,
      "expectation": {
        "seasonal_story": "Warm dirty river largemouth should favor visible cover-oriented lanes first; cleaner baitfish flies can exist only as a low-priority fallback rather than the core story.",
        "primary_lanes": [
          "compact_flipping_jig",
          "texas_rigged_soft_plastic_craw",
          "spinnerbait"
        ],
        "acceptable_secondary_lanes": [
          "bladed_jig",
          "frog_fly",
          "swim_jig",
          "clouser_minnow"
        ],
        "disallowed_lanes": [
          "drop_shot_worm"
        ],
        "expected_color_lanes": [
          "dark",
          "natural",
          "bright"
        ]
      },
      "engine_run_status": "complete",
      "archived_env_summary": [
        "Region: south_central",
        "Archive weather timezone: America/Chicago",
        "Noon air temp: 83.5 F",
        "Noon pressure: 1014.7 mb",
        "Noon cloud cover: 39%",
        "Daily high/low: 86 / 72.9 F",
        "Daily wind max: 13.5 mph",
        "Daily precip: 0.7086614173228347 in",
        "Moon phase: Waning Gibbous",
        "Sunrise/sunset: 05:44 / 20:18"
      ],
      "actual_output": {
        "top_1_lure": {
          "id": "spinnerbait",
          "display_name": "Spinnerbait",
          "score": 7.21,
          "tactical_lane": "horizontal_search",
          "color_theme": "bright",
          "color_recommendations": [
            "white/chartreuse",
            "chartreuse",
            "firetiger"
          ]
        },
        "top_3_lures": [
          {
            "id": "spinnerbait",
            "display_name": "Spinnerbait",
            "score": 7.21,
            "tactical_lane": "horizontal_search",
            "color_theme": "bright",
            "color_recommendations": [
              "white/chartreuse",
              "chartreuse",
              "firetiger"
            ]
          },
          {
            "id": "swim_jig",
            "display_name": "Swim Jig",
            "score": 7.11,
            "tactical_lane": "horizontal_search",
            "color_theme": "bright",
            "color_recommendations": [
              "white/chartreuse",
              "chartreuse",
              "firetiger"
            ]
          },
          {
            "id": "squarebill_crankbait",
            "display_name": "Squarebill Crankbait",
            "score": 6.65,
            "tactical_lane": "horizontal_search",
            "color_theme": "bright",
            "color_recommendations": [
              "white/chartreuse",
              "chartreuse",
              "firetiger"
            ]
          }
        ],
        "top_1_fly": {
          "id": "game_changer",
          "display_name": "Game Changer",
          "score": 6.2,
          "tactical_lane": "fly_baitfish",
          "color_theme": "bright",
          "color_recommendations": [
            "white/chartreuse",
            "chartreuse",
            "firetiger"
          ]
        },
        "top_3_flies": [
          {
            "id": "game_changer",
            "display_name": "Game Changer",
            "score": 6.2,
            "tactical_lane": "fly_baitfish",
            "color_theme": "bright",
            "color_recommendations": [
              "white/chartreuse",
              "chartreuse",
              "firetiger"
            ]
          },
          {
            "id": "woolly_bugger",
            "display_name": "Woolly Bugger",
            "score": 4.27,
            "tactical_lane": "fly_bottom",
            "color_theme": "bright",
            "color_recommendations": [
              "white/chartreuse",
              "chartreuse",
              "firetiger"
            ]
          },
          {
            "id": "clouser_minnow",
            "display_name": "Clouser Minnow",
            "score": 3.72,
            "tactical_lane": "fly_baitfish",
            "color_theme": "bright",
            "color_recommendations": [
              "white/chartreuse",
              "chartreuse",
              "firetiger"
            ]
          }
        ],
        "color_notes": [
          "Color of day: Bright Colors",
          "Spinnerbait: bright -> white/chartreuse, chartreuse, firetiger",
          "Swim Jig: bright -> white/chartreuse, chartreuse, firetiger",
          "Squarebill Crankbait: bright -> white/chartreuse, chartreuse, firetiger",
          "Game Changer: bright -> white/chartreuse, chartreuse, firetiger",
          "Woolly Bugger: bright -> white/chartreuse, chartreuse, firetiger",
          "Clouser Minnow: bright -> white/chartreuse, chartreuse, firetiger"
        ],
        "daily_profile_notes": [
          "Daily posture: neutral (4.9/10)",
          "Presentation presence today: bold",
          "Resolved profile: typical_column=high, likely_column_today=high, seasonal_location=shallow, posture=neutral, presentation=bold",
          "Guardrails: surface_allowed=true, suppress_true_topwater=false, suppress_fast_presentations=false, high_visibility_needed=true, column_shift_half_steps=0",
          "Variables considered: temperature_metabolic_context, temperature_trend, temperature_shock, pressure_regime, wind_condition, light_cloud_condition, runoff_flow_disruption",
          "Variables triggered: temperature_metabolic_context, temperature_trend, wind_condition, light_cloud_condition, runoff_flow_disruption",
          "Daily note: Neutral temperature metabolism keeps the day open to the normal seasonal pattern.",
          "Daily note: A warming trend nudges fish into a slightly more willing posture.",
          "Daily note: Low light opens the daily posture and supports more willingness.",
          "Daily note: Elevated flow suppresses posture and tightens fish to safer holding lanes.",
          "Daily note: Dirty water calls for more visibility and presence."
        ]
      },
      "review": {
        "precheck_flags": [
          "TOP1_PRIMARY_HIT",
          "TOP3_PRIMARY_PRESENT",
          "NO_DISALLOWED_PRESENT",
          "TOP_COLOR_MATCH:bright,bright"
        ],
        "top_1_verdict": "",
        "top_3_verdict": "",
        "scores": {
          "seasonal_fit": null,
          "daily_fit": null,
          "water_column_fit": null,
          "archetype_fit": null,
          "color_fit": null,
          "top3_variety": null,
          "boundedness": null
        },
        "failure_clusters": [],
        "notes": ""
      }
    },
    {
      "scenario_id": "lmb_newyork_aug_natural_lake_bluebird",
      "label": "Northeast largemouth, clear natural lake under bluebird conditions",
      "priority": "secondary",
      "species": "largemouth_bass",
      "context": "freshwater_lake_pond",
      "water_clarity": "clear",
      "state_code": "NY",
      "timezone": "America/New_York",
      "local_date": "2025-08-09",
      "latitude": 42.642,
      "longitude": -76.718,
      "expectation": {
        "seasonal_story": "Bluebird summer largemouth should tighten into cleaner, more controlled options.",
        "primary_lanes": [
          "wacky_rigged_stick_worm",
          "weightless_stick_worm",
          "drop_shot_worm"
        ],
        "acceptable_secondary_lanes": [
          "shaky_head_worm",
          "rabbit_strip_leech",
          "soft_jerkbait"
        ],
        "disallowed_lanes": [
          "buzzbait",
          "prop_bait"
        ],
        "expected_color_lanes": [
          "natural",
          "natural",
          "natural"
        ]
      },
      "engine_run_status": "complete",
      "archived_env_summary": [
        "Region: great_lakes_upper_midwest",
        "Archive weather timezone: America/New_York",
        "Noon air temp: 78.9 F",
        "Noon pressure: 1022.8 mb",
        "Noon cloud cover: 0%",
        "Daily high/low: 82.9 / 64.2 F",
        "Daily wind max: 7.1 mph",
        "Daily precip: 0 in",
        "Moon phase: Full Moon",
        "Sunrise/sunset: 06:06 / 20:18"
      ],
      "actual_output": {
        "top_1_lure": {
          "id": "weightless_stick_worm",
          "display_name": "Weightless Stick Worm",
          "score": 8.19,
          "tactical_lane": "finesse_subtle",
          "color_theme": "natural",
          "color_recommendations": [
            "green pumpkin",
            "olive",
            "smoke"
          ]
        },
        "top_3_lures": [
          {
            "id": "weightless_stick_worm",
            "display_name": "Weightless Stick Worm",
            "score": 8.19,
            "tactical_lane": "finesse_subtle",
            "color_theme": "natural",
            "color_recommendations": [
              "green pumpkin",
              "olive",
              "smoke"
            ]
          },
          {
            "id": "swim_jig",
            "display_name": "Swim Jig",
            "score": 5.64,
            "tactical_lane": "horizontal_search",
            "color_theme": "natural",
            "color_recommendations": [
              "green pumpkin",
              "olive",
              "smoke"
            ]
          },
          {
            "id": "paddle_tail_swimbait",
            "display_name": "Paddle-Tail Swimbait",
            "score": 4.64,
            "tactical_lane": "horizontal_search",
            "color_theme": "natural",
            "color_recommendations": [
              "green pumpkin",
              "olive",
              "smoke"
            ]
          }
        ],
        "top_1_fly": {
          "id": "woolly_bugger",
          "display_name": "Woolly Bugger",
          "score": 7.25,
          "tactical_lane": "fly_bottom",
          "color_theme": "natural",
          "color_recommendations": [
            "green pumpkin",
            "olive",
            "smoke"
          ]
        },
        "top_3_flies": [
          {
            "id": "woolly_bugger",
            "display_name": "Woolly Bugger",
            "score": 7.25,
            "tactical_lane": "fly_bottom",
            "color_theme": "natural",
            "color_recommendations": [
              "green pumpkin",
              "olive",
              "smoke"
            ]
          },
          {
            "id": "game_changer",
            "display_name": "Game Changer",
            "score": 3.48,
            "tactical_lane": "fly_baitfish",
            "color_theme": "natural",
            "color_recommendations": [
              "green pumpkin",
              "olive",
              "smoke"
            ]
          },
          {
            "id": "clouser_minnow",
            "display_name": "Clouser Minnow",
            "score": 3.23,
            "tactical_lane": "fly_baitfish",
            "color_theme": "natural",
            "color_recommendations": [
              "green pumpkin",
              "olive",
              "smoke"
            ]
          }
        ],
        "color_notes": [
          "Color of day: Natural Colors",
          "Weightless Stick Worm: natural -> green pumpkin, olive, smoke",
          "Swim Jig: natural -> green pumpkin, olive, smoke",
          "Paddle-Tail Swimbait: natural -> green pumpkin, olive, smoke",
          "Woolly Bugger: natural -> green pumpkin, olive, smoke",
          "Game Changer: natural -> green pumpkin, olive, smoke",
          "Clouser Minnow: natural -> green pumpkin, olive, smoke"
        ],
        "daily_profile_notes": [
          "Daily posture: slightly_suppressed (2.5/10)",
          "Presentation presence today: subtle",
          "Resolved profile: typical_column=high, likely_column_today=mid_high, seasonal_location=shallow_mid, posture=slightly_suppressed, presentation=subtle",
          "Guardrails: surface_allowed=false, suppress_true_topwater=true, suppress_fast_presentations=true, high_visibility_needed=false, column_shift_half_steps=1",
          "Variables considered: temperature_metabolic_context, temperature_trend, temperature_shock, pressure_regime, wind_condition, light_cloud_condition, precipitation_disruption",
          "Variables triggered: temperature_metabolic_context, temperature_trend, wind_condition, light_cloud_condition, precipitation_disruption",
          "Daily note: Heat-limited metabolism suppresses fish posture and shrinks the reliable lane.",
          "Daily note: A warming trend nudges fish into a slightly more willing posture.",
          "Daily note: Bright light trims daily willingness without fully shutting the day down.",
          "Daily note: Clear water favors a cleaner, subtler presentation."
        ]
      },
      "review": {
        "precheck_flags": [
          "TOP1_PRIMARY_HIT",
          "TOP3_PRIMARY_PRESENT",
          "NO_DISALLOWED_PRESENT",
          "TOP_COLOR_MATCH:natural,natural"
        ],
        "top_1_verdict": "",
        "top_3_verdict": "",
        "scores": {
          "seasonal_fit": null,
          "daily_fit": null,
          "water_column_fit": null,
          "archetype_fit": null,
          "color_fit": null,
          "top3_variety": null,
          "boundedness": null
        },
        "failure_clusters": [],
        "notes": ""
      }
    },
    {
      "scenario_id": "lmb_louisiana_sep_shallow_grass",
      "label": "Louisiana largemouth, early-fall stained grass pattern",
      "priority": "core",
      "species": "largemouth_bass",
      "context": "freshwater_lake_pond",
      "water_clarity": "stained",
      "state_code": "LA",
      "timezone": "America/Chicago",
      "local_date": "2025-09-17",
      "latitude": 30.208,
      "longitude": -92.329,
      "expectation": {
        "seasonal_story": "Early-fall southern largemouth should open surface and horizontal cover lanes more freely than summer bluebird windows.",
        "primary_lanes": [
          "walking_topwater",
          "swim_jig",
          "spinnerbait"
        ],
        "acceptable_secondary_lanes": [
          "hollow_body_frog",
          "bladed_jig",
          "popper_fly"
        ],
        "disallowed_lanes": [
          "blade_bait"
        ],
        "expected_color_lanes": [
          "natural",
          "natural",
          "bright"
        ]
      },
      "engine_run_status": "complete",
      "archived_env_summary": [
        "Region: gulf_coast",
        "Archive weather timezone: America/Chicago",
        "Noon air temp: 88.2 F",
        "Noon pressure: 1017.4 mb",
        "Noon cloud cover: 2%",
        "Daily high/low: 90.6 / 72.4 F",
        "Daily wind max: 7.5 mph",
        "Daily precip: 0.03543307086614173 in",
        "Moon phase: Waning Crescent",
        "Sunrise/sunset: 06:54 / 19:13"
      ],
      "actual_output": {
        "top_1_lure": {
          "id": "spinnerbait",
          "display_name": "Spinnerbait",
          "score": 3.19,
          "tactical_lane": "horizontal_search",
          "color_theme": "dark",
          "color_recommendations": [
            "black",
            "black/blue",
            "black/purple"
          ]
        },
        "top_3_lures": [
          {
            "id": "spinnerbait",
            "display_name": "Spinnerbait",
            "score": 3.19,
            "tactical_lane": "horizontal_search",
            "color_theme": "dark",
            "color_recommendations": [
              "black",
              "black/blue",
              "black/purple"
            ]
          },
          {
            "id": "bladed_jig",
            "display_name": "Bladed Jig",
            "score": 2.99,
            "tactical_lane": "horizontal_search",
            "color_theme": "dark",
            "color_recommendations": [
              "black",
              "black/blue",
              "black/purple"
            ]
          },
          {
            "id": "swim_jig",
            "display_name": "Swim Jig",
            "score": 2.84,
            "tactical_lane": "horizontal_search",
            "color_theme": "dark",
            "color_recommendations": [
              "black",
              "black/blue",
              "black/purple"
            ]
          }
        ],
        "top_1_fly": {
          "id": "clouser_minnow",
          "display_name": "Clouser Minnow",
          "score": 3.21,
          "tactical_lane": "fly_baitfish",
          "color_theme": "dark",
          "color_recommendations": [
            "black",
            "black/blue",
            "black/purple"
          ]
        },
        "top_3_flies": [
          {
            "id": "clouser_minnow",
            "display_name": "Clouser Minnow",
            "score": 3.21,
            "tactical_lane": "fly_baitfish",
            "color_theme": "dark",
            "color_recommendations": [
              "black",
              "black/blue",
              "black/purple"
            ]
          },
          {
            "id": "game_changer",
            "display_name": "Game Changer",
            "score": 2.11,
            "tactical_lane": "fly_baitfish",
            "color_theme": "dark",
            "color_recommendations": [
              "black",
              "black/blue",
              "black/purple"
            ]
          },
          {
            "id": "articulated_baitfish_streamer",
            "display_name": "Articulated Baitfish Streamer",
            "score": 0.91,
            "tactical_lane": "fly_baitfish",
            "color_theme": "dark",
            "color_recommendations": [
              "black",
              "black/blue",
              "black/purple"
            ]
          }
        ],
        "color_notes": [
          "Color of day: Dark Colors",
          "Spinnerbait: dark -> black, black/blue, black/purple",
          "Bladed Jig: dark -> black, black/blue, black/purple",
          "Swim Jig: dark -> black, black/blue, black/purple",
          "Clouser Minnow: dark -> black, black/blue, black/purple",
          "Game Changer: dark -> black, black/blue, black/purple",
          "Articulated Baitfish Streamer: dark -> black, black/blue, black/purple"
        ],
        "daily_profile_notes": [
          "Daily posture: suppressed (2.3/10)",
          "Presentation presence today: subtle",
          "Resolved profile: typical_column=high, likely_column_today=mid, seasonal_location=shallow_mid, posture=suppressed, presentation=subtle",
          "Guardrails: surface_allowed=false, suppress_true_topwater=true, suppress_fast_presentations=true, high_visibility_needed=false, column_shift_half_steps=2",
          "Variables considered: temperature_metabolic_context, temperature_trend, temperature_shock, pressure_regime, wind_condition, light_cloud_condition, precipitation_disruption",
          "Variables triggered: temperature_metabolic_context, temperature_trend, wind_condition, light_cloud_condition, precipitation_disruption",
          "Daily note: Heat-limited metabolism suppresses fish posture and shrinks the reliable lane.",
          "Daily note: A warming trend nudges fish into a slightly more willing posture.",
          "Daily note: Bright light trims daily willingness without fully shutting the day down.",
          "Daily note: Stained water supports a balanced presentation with some extra presence."
        ]
      },
      "review": {
        "precheck_flags": [
          "TOP1_PRIMARY_HIT",
          "TOP3_PRIMARY_PRESENT",
          "NO_DISALLOWED_PRESENT",
          "TOP_COLOR_MATCH:dark,dark"
        ],
        "top_1_verdict": "",
        "top_3_verdict": "",
        "scores": {
          "seasonal_fit": null,
          "daily_fit": null,
          "water_column_fit": null,
          "archetype_fit": null,
          "color_fit": null,
          "top3_variety": null,
          "boundedness": null
        },
        "failure_clusters": [],
        "notes": ""
      }
    },
    {
      "scenario_id": "lmb_ozarks_oct_shad_transition",
      "label": "Ozarks largemouth, fall shad transition reservoir day",
      "priority": "core",
      "species": "largemouth_bass",
      "context": "freshwater_lake_pond",
      "water_clarity": "clear",
      "state_code": "MO",
      "timezone": "America/Chicago",
      "local_date": "2025-10-11",
      "latitude": 36.525,
      "longitude": -93.214,
      "expectation": {
        "seasonal_story": "Fall largemouth should strongly respect baitfish transition lanes, and on calm mixed-light shad days a suspending jerkbait can lead without breaking the transition story.",
        "primary_lanes": [
          "squarebill_crankbait",
          "spinnerbait",
          "paddle_tail_swimbait",
          "suspending_jerkbait"
        ],
        "acceptable_secondary_lanes": [
          "soft_jerkbait",
          "flat_sided_crankbait",
          "game_changer"
        ],
        "disallowed_lanes": [
          "texas_rigged_soft_plastic_craw"
        ],
        "expected_color_lanes": [
          "natural",
          "natural",
          "bright"
        ]
      },
      "engine_run_status": "complete",
      "archived_env_summary": [
        "Region: south_central",
        "Archive weather timezone: America/Chicago",
        "Noon air temp: 70.2 F",
        "Noon pressure: 1018.4 mb",
        "Noon cloud cover: 40%",
        "Daily high/low: 76.1 / 55.5 F",
        "Daily wind max: 6.8 mph",
        "Daily precip: 0 in",
        "Moon phase: Waning Gibbous",
        "Sunrise/sunset: 07:15 / 18:43"
      ],
      "actual_output": {
        "top_1_lure": {
          "id": "suspending_jerkbait",
          "display_name": "Suspending Jerkbait",
          "score": 5.93,
          "tactical_lane": "reaction_mid_column",
          "color_theme": "natural",
          "color_recommendations": [
            "green pumpkin",
            "olive",
            "smoke"
          ]
        },
        "top_3_lures": [
          {
            "id": "suspending_jerkbait",
            "display_name": "Suspending Jerkbait",
            "score": 5.93,
            "tactical_lane": "reaction_mid_column",
            "color_theme": "natural",
            "color_recommendations": [
              "green pumpkin",
              "olive",
              "smoke"
            ]
          },
          {
            "id": "flat_sided_crankbait",
            "display_name": "Flat-Sided Crankbait",
            "score": 5.62,
            "tactical_lane": "reaction_mid_column",
            "color_theme": "natural",
            "color_recommendations": [
              "green pumpkin",
              "olive",
              "smoke"
            ]
          },
          {
            "id": "paddle_tail_swimbait",
            "display_name": "Paddle-Tail Swimbait",
            "score": 5.72,
            "tactical_lane": "horizontal_search",
            "color_theme": "natural",
            "color_recommendations": [
              "green pumpkin",
              "olive",
              "smoke"
            ]
          }
        ],
        "top_1_fly": {
          "id": "clouser_minnow",
          "display_name": "Clouser Minnow",
          "score": 4.78,
          "tactical_lane": "fly_baitfish",
          "color_theme": "natural",
          "color_recommendations": [
            "green pumpkin",
            "olive",
            "smoke"
          ]
        },
        "top_3_flies": [
          {
            "id": "clouser_minnow",
            "display_name": "Clouser Minnow",
            "score": 4.78,
            "tactical_lane": "fly_baitfish",
            "color_theme": "natural",
            "color_recommendations": [
              "green pumpkin",
              "olive",
              "smoke"
            ]
          },
          {
            "id": "woolly_bugger",
            "display_name": "Woolly Bugger",
            "score": 4.7,
            "tactical_lane": "fly_bottom",
            "color_theme": "natural",
            "color_recommendations": [
              "green pumpkin",
              "olive",
              "smoke"
            ]
          },
          {
            "id": "deceiver",
            "display_name": "Deceiver",
            "score": 4.08,
            "tactical_lane": "fly_baitfish",
            "color_theme": "natural",
            "color_recommendations": [
              "green pumpkin",
              "olive",
              "smoke"
            ]
          }
        ],
        "color_notes": [
          "Color of day: Natural Colors",
          "Suspending Jerkbait: natural -> green pumpkin, olive, smoke",
          "Flat-Sided Crankbait: natural -> green pumpkin, olive, smoke",
          "Paddle-Tail Swimbait: natural -> green pumpkin, olive, smoke",
          "Clouser Minnow: natural -> green pumpkin, olive, smoke",
          "Woolly Bugger: natural -> green pumpkin, olive, smoke",
          "Deceiver: natural -> green pumpkin, olive, smoke"
        ],
        "daily_profile_notes": [
          "Daily posture: neutral (5.8/10)",
          "Presentation presence today: subtle",
          "Resolved profile: typical_column=mid, likely_column_today=mid, seasonal_location=shallow_mid, posture=neutral, presentation=subtle",
          "Guardrails: surface_allowed=true, suppress_true_topwater=false, suppress_fast_presentations=false, high_visibility_needed=false, column_shift_half_steps=0",
          "Variables considered: temperature_metabolic_context, temperature_trend, temperature_shock, pressure_regime, wind_condition, light_cloud_condition, precipitation_disruption",
          "Variables triggered: temperature_metabolic_context, temperature_trend, wind_condition, light_cloud_condition, precipitation_disruption",
          "Daily note: Neutral temperature metabolism keeps the day open to the normal seasonal pattern.",
          "Daily note: A warming trend nudges fish into a slightly more willing posture.",
          "Daily note: Clear water favors a cleaner, subtler presentation."
        ]
      },
      "review": {
        "precheck_flags": [
          "TOP1_PRIMARY_HIT",
          "TOP3_PRIMARY_PRESENT",
          "NO_DISALLOWED_PRESENT",
          "TOP_COLOR_MATCH:natural,natural"
        ],
        "top_1_verdict": "",
        "top_3_verdict": "",
        "scores": {
          "seasonal_fit": null,
          "daily_fit": null,
          "water_column_fit": null,
          "archetype_fit": null,
          "color_fit": null,
          "top3_variety": null,
          "boundedness": null
        },
        "failure_clusters": [],
        "notes": ""
      }
    },
    {
      "scenario_id": "lmb_texas_dec_pond_cold_clear",
      "label": "Texas pond largemouth, early-winter clear slowdown",
      "priority": "core",
      "species": "largemouth_bass",
      "context": "freshwater_lake_pond",
      "water_clarity": "clear",
      "state_code": "TX",
      "timezone": "America/Chicago",
      "local_date": "2025-12-14",
      "latitude": 32.7767,
      "longitude": -96.797,
      "expectation": {
        "seasonal_story": "Early-winter largemouth should tighten to slower lower-column lanes with only mild daily openings.",
        "primary_lanes": [
          "football_jig",
          "shaky_head_worm",
          "suspending_jerkbait"
        ],
        "acceptable_secondary_lanes": [
          "blade_bait",
          "rabbit_strip_leech"
        ],
        "disallowed_lanes": [
          "walking_topwater",
          "hollow_body_frog"
        ],
        "expected_color_lanes": [
          "natural",
          "dark",
          "natural"
        ]
      },
      "engine_run_status": "complete",
      "archived_env_summary": [
        "Region: south_central",
        "Archive weather timezone: America/Chicago",
        "Noon air temp: 34 F",
        "Noon pressure: 1038.7 mb",
        "Noon cloud cover: 100%",
        "Daily high/low: 49.3 / 27.6 F",
        "Daily wind max: 7.3 mph",
        "Daily precip: 0 in",
        "Moon phase: Waning Crescent",
        "Sunrise/sunset: 07:20 / 17:23"
      ],
      "actual_output": {
        "top_1_lure": {
          "id": "football_jig",
          "display_name": "Football Jig",
          "score": 7.94,
          "tactical_lane": "bottom_contact",
          "color_theme": "natural",
          "color_recommendations": [
            "green pumpkin",
            "olive",
            "smoke"
          ]
        },
        "top_3_lures": [
          {
            "id": "football_jig",
            "display_name": "Football Jig",
            "score": 7.94,
            "tactical_lane": "bottom_contact",
            "color_theme": "natural",
            "color_recommendations": [
              "green pumpkin",
              "olive",
              "smoke"
            ]
          },
          {
            "id": "shaky_head_worm",
            "display_name": "Shaky-Head Worm",
            "score": 7.27,
            "tactical_lane": "bottom_contact",
            "color_theme": "natural",
            "color_recommendations": [
              "green pumpkin",
              "olive",
              "smoke"
            ]
          },
          {
            "id": "texas_rigged_soft_plastic_craw",
            "display_name": "Texas-Rigged Soft-Plastic Craw",
            "score": 4.73,
            "tactical_lane": "cover_weedless",
            "color_theme": "natural",
            "color_recommendations": [
              "green pumpkin",
              "olive",
              "smoke"
            ]
          }
        ],
        "top_1_fly": {
          "id": "rabbit_strip_leech",
          "display_name": "Rabbit-Strip Leech",
          "score": 8.59,
          "tactical_lane": "fly_bottom",
          "color_theme": "natural",
          "color_recommendations": [
            "green pumpkin",
            "olive",
            "smoke"
          ]
        },
        "top_3_flies": [
          {
            "id": "rabbit_strip_leech",
            "display_name": "Rabbit-Strip Leech",
            "score": 8.59,
            "tactical_lane": "fly_bottom",
            "color_theme": "natural",
            "color_recommendations": [
              "green pumpkin",
              "olive",
              "smoke"
            ]
          },
          {
            "id": "sculpin_streamer",
            "display_name": "Sculpin Streamer",
            "score": 8.59,
            "tactical_lane": "fly_bottom",
            "color_theme": "natural",
            "color_recommendations": [
              "green pumpkin",
              "olive",
              "smoke"
            ]
          },
          {
            "id": "balanced_leech",
            "display_name": "Balanced Leech",
            "score": 8.59,
            "tactical_lane": "fly_bottom",
            "color_theme": "natural",
            "color_recommendations": [
              "green pumpkin",
              "olive",
              "smoke"
            ]
          }
        ],
        "color_notes": [
          "Color of day: Natural Colors",
          "Football Jig: natural -> green pumpkin, olive, smoke",
          "Shaky-Head Worm: natural -> green pumpkin, olive, smoke",
          "Texas-Rigged Soft-Plastic Craw: natural -> green pumpkin, olive, smoke",
          "Rabbit-Strip Leech: natural -> green pumpkin, olive, smoke",
          "Sculpin Streamer: natural -> green pumpkin, olive, smoke",
          "Balanced Leech: natural -> green pumpkin, olive, smoke"
        ],
        "daily_profile_notes": [
          "Daily posture: suppressed (2.4/10)",
          "Presentation presence today: subtle",
          "Resolved profile: typical_column=low, likely_column_today=low, seasonal_location=deep, posture=suppressed, presentation=subtle",
          "Guardrails: surface_allowed=false, suppress_true_topwater=true, suppress_fast_presentations=true, high_visibility_needed=false, column_shift_half_steps=2",
          "Variables considered: temperature_metabolic_context, temperature_trend, temperature_shock, pressure_regime, wind_condition, light_cloud_condition, precipitation_disruption",
          "Variables triggered: temperature_metabolic_context, temperature_trend, wind_condition, light_cloud_condition, precipitation_disruption",
          "Daily note: Cold-limited metabolism suppresses fish posture and tightens the bite lane.",
          "Daily note: A cooling trend tightens fish and reduces daily willingness.",
          "Daily note: Moderate chop supports a slightly more open lake posture.",
          "Daily note: Clear water favors a cleaner, subtler presentation."
        ]
      },
      "review": {
        "precheck_flags": [
          "TOP1_PRIMARY_HIT",
          "TOP3_PRIMARY_PRESENT",
          "NO_DISALLOWED_PRESENT",
          "TOP_COLOR_MATCH:natural,natural"
        ],
        "top_1_verdict": "",
        "top_3_verdict": "",
        "scores": {
          "seasonal_fit": null,
          "daily_fit": null,
          "water_column_fit": null,
          "archetype_fit": null,
          "color_fit": null,
          "top3_variety": null,
          "boundedness": null
        },
        "failure_clusters": [],
        "notes": ""
      }
    }
  ]
}
