{
  "generated_at": "2026-04-04T21:02:33.200Z",
  "total_scenarios": 68,
  "core_monthly_count": 48,
  "overlay_count": 20,
  "anchors": [
    {
      "key": "appalachian_tailwater",
      "label": "Appalachian clear tailwater",
      "latitude": 35.4306,
      "longitude": -83.4477,
      "state_code": "NC",
      "timezone": "America/New_York",
      "context": "freshwater_river",
      "region_key": "appalachian",
      "default_clarity": "clear",
      "audit_role": "core_monthly",
      "notes": "Core trout restraint benchmark for tailwater winter control, bluebird summer tightening, and flow-bump minnow windows."
    },
    {
      "key": "northeast_freestone",
      "label": "Northeast freestone river",
      "latitude": 41.7268,
      "longitude": -77.4529,
      "state_code": "PA",
      "timezone": "America/New_York",
      "context": "freshwater_river",
      "region_key": "northeast",
      "default_clarity": "clear",
      "audit_role": "core_monthly",
      "notes": "Core northern freestone benchmark for winter subtlety, spring minnow openings, and late-fall high-water discipline."
    },
    {
      "key": "mountain_west_river",
      "label": "Mountain West trout river",
      "latitude": 38.4783,
      "longitude": -107.8762,
      "state_code": "CO",
      "timezone": "America/Denver",
      "context": "freshwater_river",
      "region_key": "mountain_west",
      "default_clarity": "clear",
      "audit_role": "core_monthly",
      "notes": "Core western trout benchmark for shoulder-season minnow control, runoff-edge transitions, and clear fall baitfish streamer behavior."
    },
    {
      "key": "pacific_northwest_river",
      "label": "Pacific Northwest trout river",
      "latitude": 44.3539,
      "longitude": -121.5498,
      "state_code": "OR",
      "timezone": "America/Los_Angeles",
      "context": "freshwater_river",
      "region_key": "pacific_northwest",
      "default_clarity": "clear",
      "audit_role": "core_monthly",
      "notes": "Core northwest benchmark for early-summer streamer openings, low-water summer control, and late-fall minnow tightening."
    },
    {
      "key": "northern_california_fall",
      "label": "Northern California trout river",
      "latitude": 41.7922,
      "longitude": -122.6217,
      "state_code": "CA",
      "timezone": "America/Los_Angeles",
      "context": "freshwater_river",
      "region_key": "northern_california",
      "default_clarity": "clear",
      "audit_role": "seasonal_overlay",
      "notes": "Fall and shoulder-season western overlay where articulated baitfish, game changer, and late-fall control must stay sensible."
    },
    {
      "key": "great_lakes_highwater",
      "label": "Great Lakes / Upper Midwest trout river",
      "latitude": 46.0042,
      "longitude": -89.6651,
      "state_code": "WI",
      "timezone": "America/Chicago",
      "context": "freshwater_river",
      "region_key": "great_lakes_upper_midwest",
      "default_clarity": "stained",
      "audit_role": "seasonal_overlay",
      "notes": "Northern high-water overlay for stained visibility, late-fall tightening, and spring cold-water discipline."
    },
    {
      "key": "alaska_big_river",
      "label": "Alaska trout river",
      "latitude": 61.5799,
      "longitude": -149.4411,
      "state_code": "AK",
      "timezone": "America/Anchorage",
      "context": "freshwater_river",
      "region_key": "alaska",
      "default_clarity": "clear",
      "audit_role": "seasonal_overlay",
      "notes": "Big-water trout overlay for strong fall baitfish windows and early-winter heavy-streamer control."
    },
    {
      "key": "idaho_runoff_edge",
      "label": "Idaho runoff-edge trout river",
      "latitude": 44.0772,
      "longitude": -114.742,
      "state_code": "ID",
      "timezone": "America/Boise",
      "context": "freshwater_river",
      "region_key": "mountain_west",
      "default_clarity": "stained",
      "audit_role": "seasonal_overlay",
      "notes": "Runoff-edge overlay to stress trout visibility, spinner support, and midsummer restraint when the water has color."
    },
    {
      "key": "south_central_tailwater",
      "label": "South-central tailwater trout river",
      "latitude": 35.4409,
      "longitude": -84.6013,
      "state_code": "TN",
      "timezone": "America/New_York",
      "context": "freshwater_river",
      "region_key": "south_central",
      "default_clarity": "stained",
      "audit_role": "seasonal_overlay",
      "notes": "Warm-tailwater overlay for stained generation pulses, summer restraint, and current-aware trout reads outside classic coldwater regions."
    }
  ],
  "scenarios": [
    {
      "id": "trout_matrix_appalachian_tailwater_01",
      "anchor_key": "appalachian_tailwater",
      "label": "Appalachian clear tailwater, winter control month 1",
      "month": 1,
      "local_date": "2025-01-16",
      "state_code": "NC",
      "timezone": "America/New_York",
      "latitude": 35.4306,
      "longitude": -83.4477,
      "context": "freshwater_river",
      "region_key": "appalachian",
      "default_clarity": "clear",
      "matrix_role": "core_monthly",
      "focus_window": "winter_control"
    },
    {
      "id": "trout_matrix_appalachian_tailwater_02",
      "anchor_key": "appalachian_tailwater",
      "label": "Appalachian clear tailwater, prespawn opening month 2",
      "month": 2,
      "local_date": "2025-02-19",
      "state_code": "NC",
      "timezone": "America/New_York",
      "latitude": 35.4306,
      "longitude": -83.4477,
      "context": "freshwater_river",
      "region_key": "appalachian",
      "default_clarity": "clear",
      "matrix_role": "core_monthly",
      "focus_window": "prespawn_opening"
    },
    {
      "id": "trout_matrix_appalachian_tailwater_03",
      "anchor_key": "appalachian_tailwater",
      "label": "Appalachian clear tailwater, prespawn opening month 3",
      "month": 3,
      "local_date": "2025-03-20",
      "state_code": "NC",
      "timezone": "America/New_York",
      "latitude": 35.4306,
      "longitude": -83.4477,
      "context": "freshwater_river",
      "region_key": "appalachian",
      "default_clarity": "clear",
      "matrix_role": "core_monthly",
      "focus_window": "prespawn_opening"
    },
    {
      "id": "trout_matrix_appalachian_tailwater_04",
      "anchor_key": "appalachian_tailwater",
      "label": "Appalachian clear tailwater, spawn postspawn transition month 4",
      "month": 4,
      "local_date": "2025-04-16",
      "state_code": "NC",
      "timezone": "America/New_York",
      "latitude": 35.4306,
      "longitude": -83.4477,
      "context": "freshwater_river",
      "region_key": "appalachian",
      "default_clarity": "clear",
      "matrix_role": "core_monthly",
      "focus_window": "spawn_postspawn_transition"
    },
    {
      "id": "trout_matrix_appalachian_tailwater_05",
      "anchor_key": "appalachian_tailwater",
      "label": "Appalachian clear tailwater, spawn postspawn transition month 5",
      "month": 5,
      "local_date": "2025-05-15",
      "state_code": "NC",
      "timezone": "America/New_York",
      "latitude": 35.4306,
      "longitude": -83.4477,
      "context": "freshwater_river",
      "region_key": "appalachian",
      "default_clarity": "clear",
      "matrix_role": "core_monthly",
      "focus_window": "spawn_postspawn_transition"
    },
    {
      "id": "trout_matrix_appalachian_tailwater_06",
      "anchor_key": "appalachian_tailwater",
      "label": "Appalachian clear tailwater, summer positioning month 6",
      "month": 6,
      "local_date": "2025-06-18",
      "state_code": "NC",
      "timezone": "America/New_York",
      "latitude": 35.4306,
      "longitude": -83.4477,
      "context": "freshwater_river",
      "region_key": "appalachian",
      "default_clarity": "clear",
      "matrix_role": "core_monthly",
      "focus_window": "summer_positioning"
    },
    {
      "id": "trout_matrix_appalachian_tailwater_07",
      "anchor_key": "appalachian_tailwater",
      "label": "Appalachian clear tailwater, summer positioning month 7",
      "month": 7,
      "local_date": "2025-07-16",
      "state_code": "NC",
      "timezone": "America/New_York",
      "latitude": 35.4306,
      "longitude": -83.4477,
      "context": "freshwater_river",
      "region_key": "appalachian",
      "default_clarity": "clear",
      "matrix_role": "core_monthly",
      "focus_window": "summer_positioning"
    },
    {
      "id": "trout_matrix_appalachian_tailwater_08",
      "anchor_key": "appalachian_tailwater",
      "label": "Appalachian clear tailwater, summer positioning month 8",
      "month": 8,
      "local_date": "2025-08-14",
      "state_code": "NC",
      "timezone": "America/New_York",
      "latitude": 35.4306,
      "longitude": -83.4477,
      "context": "freshwater_river",
      "region_key": "appalachian",
      "default_clarity": "clear",
      "matrix_role": "core_monthly",
      "focus_window": "summer_positioning"
    },
    {
      "id": "trout_matrix_appalachian_tailwater_09",
      "anchor_key": "appalachian_tailwater",
      "label": "Appalachian clear tailwater, fall transition month 9",
      "month": 9,
      "local_date": "2025-09-17",
      "state_code": "NC",
      "timezone": "America/New_York",
      "latitude": 35.4306,
      "longitude": -83.4477,
      "context": "freshwater_river",
      "region_key": "appalachian",
      "default_clarity": "clear",
      "matrix_role": "core_monthly",
      "focus_window": "fall_transition"
    },
    {
      "id": "trout_matrix_appalachian_tailwater_10",
      "anchor_key": "appalachian_tailwater",
      "label": "Appalachian clear tailwater, fall transition month 10",
      "month": 10,
      "local_date": "2025-10-15",
      "state_code": "NC",
      "timezone": "America/New_York",
      "latitude": 35.4306,
      "longitude": -83.4477,
      "context": "freshwater_river",
      "region_key": "appalachian",
      "default_clarity": "clear",
      "matrix_role": "core_monthly",
      "focus_window": "fall_transition"
    },
    {
      "id": "trout_matrix_appalachian_tailwater_11",
      "anchor_key": "appalachian_tailwater",
      "label": "Appalachian clear tailwater, fall transition month 11",
      "month": 11,
      "local_date": "2025-11-12",
      "state_code": "NC",
      "timezone": "America/New_York",
      "latitude": 35.4306,
      "longitude": -83.4477,
      "context": "freshwater_river",
      "region_key": "appalachian",
      "default_clarity": "clear",
      "matrix_role": "core_monthly",
      "focus_window": "fall_transition"
    },
    {
      "id": "trout_matrix_appalachian_tailwater_12",
      "anchor_key": "appalachian_tailwater",
      "label": "Appalachian clear tailwater, winter control month 12",
      "month": 12,
      "local_date": "2025-12-10",
      "state_code": "NC",
      "timezone": "America/New_York",
      "latitude": 35.4306,
      "longitude": -83.4477,
      "context": "freshwater_river",
      "region_key": "appalachian",
      "default_clarity": "clear",
      "matrix_role": "core_monthly",
      "focus_window": "winter_control"
    },
    {
      "id": "trout_matrix_northeast_freestone_01",
      "anchor_key": "northeast_freestone",
      "label": "Northeast freestone river, winter control month 1",
      "month": 1,
      "local_date": "2025-01-16",
      "state_code": "PA",
      "timezone": "America/New_York",
      "latitude": 41.7268,
      "longitude": -77.4529,
      "context": "freshwater_river",
      "region_key": "northeast",
      "default_clarity": "clear",
      "matrix_role": "core_monthly",
      "focus_window": "winter_control"
    },
    {
      "id": "trout_matrix_northeast_freestone_02",
      "anchor_key": "northeast_freestone",
      "label": "Northeast freestone river, prespawn opening month 2",
      "month": 2,
      "local_date": "2025-02-19",
      "state_code": "PA",
      "timezone": "America/New_York",
      "latitude": 41.7268,
      "longitude": -77.4529,
      "context": "freshwater_river",
      "region_key": "northeast",
      "default_clarity": "clear",
      "matrix_role": "core_monthly",
      "focus_window": "prespawn_opening"
    },
    {
      "id": "trout_matrix_northeast_freestone_03",
      "anchor_key": "northeast_freestone",
      "label": "Northeast freestone river, prespawn opening month 3",
      "month": 3,
      "local_date": "2025-03-20",
      "state_code": "PA",
      "timezone": "America/New_York",
      "latitude": 41.7268,
      "longitude": -77.4529,
      "context": "freshwater_river",
      "region_key": "northeast",
      "default_clarity": "clear",
      "matrix_role": "core_monthly",
      "focus_window": "prespawn_opening"
    },
    {
      "id": "trout_matrix_northeast_freestone_04",
      "anchor_key": "northeast_freestone",
      "label": "Northeast freestone river, spawn postspawn transition month 4",
      "month": 4,
      "local_date": "2025-04-16",
      "state_code": "PA",
      "timezone": "America/New_York",
      "latitude": 41.7268,
      "longitude": -77.4529,
      "context": "freshwater_river",
      "region_key": "northeast",
      "default_clarity": "clear",
      "matrix_role": "core_monthly",
      "focus_window": "spawn_postspawn_transition"
    },
    {
      "id": "trout_matrix_northeast_freestone_05",
      "anchor_key": "northeast_freestone",
      "label": "Northeast freestone river, spawn postspawn transition month 5",
      "month": 5,
      "local_date": "2025-05-15",
      "state_code": "PA",
      "timezone": "America/New_York",
      "latitude": 41.7268,
      "longitude": -77.4529,
      "context": "freshwater_river",
      "region_key": "northeast",
      "default_clarity": "clear",
      "matrix_role": "core_monthly",
      "focus_window": "spawn_postspawn_transition"
    },
    {
      "id": "trout_matrix_northeast_freestone_06",
      "anchor_key": "northeast_freestone",
      "label": "Northeast freestone river, summer positioning month 6",
      "month": 6,
      "local_date": "2025-06-18",
      "state_code": "PA",
      "timezone": "America/New_York",
      "latitude": 41.7268,
      "longitude": -77.4529,
      "context": "freshwater_river",
      "region_key": "northeast",
      "default_clarity": "clear",
      "matrix_role": "core_monthly",
      "focus_window": "summer_positioning"
    },
    {
      "id": "trout_matrix_northeast_freestone_07",
      "anchor_key": "northeast_freestone",
      "label": "Northeast freestone river, summer positioning month 7",
      "month": 7,
      "local_date": "2025-07-16",
      "state_code": "PA",
      "timezone": "America/New_York",
      "latitude": 41.7268,
      "longitude": -77.4529,
      "context": "freshwater_river",
      "region_key": "northeast",
      "default_clarity": "clear",
      "matrix_role": "core_monthly",
      "focus_window": "summer_positioning"
    },
    {
      "id": "trout_matrix_northeast_freestone_08",
      "anchor_key": "northeast_freestone",
      "label": "Northeast freestone river, summer positioning month 8",
      "month": 8,
      "local_date": "2025-08-14",
      "state_code": "PA",
      "timezone": "America/New_York",
      "latitude": 41.7268,
      "longitude": -77.4529,
      "context": "freshwater_river",
      "region_key": "northeast",
      "default_clarity": "clear",
      "matrix_role": "core_monthly",
      "focus_window": "summer_positioning"
    },
    {
      "id": "trout_matrix_northeast_freestone_09",
      "anchor_key": "northeast_freestone",
      "label": "Northeast freestone river, fall transition month 9",
      "month": 9,
      "local_date": "2025-09-17",
      "state_code": "PA",
      "timezone": "America/New_York",
      "latitude": 41.7268,
      "longitude": -77.4529,
      "context": "freshwater_river",
      "region_key": "northeast",
      "default_clarity": "clear",
      "matrix_role": "core_monthly",
      "focus_window": "fall_transition"
    },
    {
      "id": "trout_matrix_northeast_freestone_10",
      "anchor_key": "northeast_freestone",
      "label": "Northeast freestone river, fall transition month 10",
      "month": 10,
      "local_date": "2025-10-15",
      "state_code": "PA",
      "timezone": "America/New_York",
      "latitude": 41.7268,
      "longitude": -77.4529,
      "context": "freshwater_river",
      "region_key": "northeast",
      "default_clarity": "clear",
      "matrix_role": "core_monthly",
      "focus_window": "fall_transition"
    },
    {
      "id": "trout_matrix_northeast_freestone_11",
      "anchor_key": "northeast_freestone",
      "label": "Northeast freestone river, fall transition month 11",
      "month": 11,
      "local_date": "2025-11-12",
      "state_code": "PA",
      "timezone": "America/New_York",
      "latitude": 41.7268,
      "longitude": -77.4529,
      "context": "freshwater_river",
      "region_key": "northeast",
      "default_clarity": "clear",
      "matrix_role": "core_monthly",
      "focus_window": "fall_transition"
    },
    {
      "id": "trout_matrix_northeast_freestone_12",
      "anchor_key": "northeast_freestone",
      "label": "Northeast freestone river, winter control month 12",
      "month": 12,
      "local_date": "2025-12-10",
      "state_code": "PA",
      "timezone": "America/New_York",
      "latitude": 41.7268,
      "longitude": -77.4529,
      "context": "freshwater_river",
      "region_key": "northeast",
      "default_clarity": "clear",
      "matrix_role": "core_monthly",
      "focus_window": "winter_control"
    },
    {
      "id": "trout_matrix_mountain_west_river_01",
      "anchor_key": "mountain_west_river",
      "label": "Mountain West trout river, winter control month 1",
      "month": 1,
      "local_date": "2025-01-16",
      "state_code": "CO",
      "timezone": "America/Denver",
      "latitude": 38.4783,
      "longitude": -107.8762,
      "context": "freshwater_river",
      "region_key": "mountain_west",
      "default_clarity": "clear",
      "matrix_role": "core_monthly",
      "focus_window": "winter_control"
    },
    {
      "id": "trout_matrix_mountain_west_river_02",
      "anchor_key": "mountain_west_river",
      "label": "Mountain West trout river, prespawn opening month 2",
      "month": 2,
      "local_date": "2025-02-19",
      "state_code": "CO",
      "timezone": "America/Denver",
      "latitude": 38.4783,
      "longitude": -107.8762,
      "context": "freshwater_river",
      "region_key": "mountain_west",
      "default_clarity": "clear",
      "matrix_role": "core_monthly",
      "focus_window": "prespawn_opening"
    },
    {
      "id": "trout_matrix_mountain_west_river_03",
      "anchor_key": "mountain_west_river",
      "label": "Mountain West trout river, prespawn opening month 3",
      "month": 3,
      "local_date": "2025-03-20",
      "state_code": "CO",
      "timezone": "America/Denver",
      "latitude": 38.4783,
      "longitude": -107.8762,
      "context": "freshwater_river",
      "region_key": "mountain_west",
      "default_clarity": "clear",
      "matrix_role": "core_monthly",
      "focus_window": "prespawn_opening"
    },
    {
      "id": "trout_matrix_mountain_west_river_04",
      "anchor_key": "mountain_west_river",
      "label": "Mountain West trout river, spawn postspawn transition month 4",
      "month": 4,
      "local_date": "2025-04-16",
      "state_code": "CO",
      "timezone": "America/Denver",
      "latitude": 38.4783,
      "longitude": -107.8762,
      "context": "freshwater_river",
      "region_key": "mountain_west",
      "default_clarity": "clear",
      "matrix_role": "core_monthly",
      "focus_window": "spawn_postspawn_transition"
    },
    {
      "id": "trout_matrix_mountain_west_river_05",
      "anchor_key": "mountain_west_river",
      "label": "Mountain West trout river, spawn postspawn transition month 5",
      "month": 5,
      "local_date": "2025-05-15",
      "state_code": "CO",
      "timezone": "America/Denver",
      "latitude": 38.4783,
      "longitude": -107.8762,
      "context": "freshwater_river",
      "region_key": "mountain_west",
      "default_clarity": "clear",
      "matrix_role": "core_monthly",
      "focus_window": "spawn_postspawn_transition"
    },
    {
      "id": "trout_matrix_mountain_west_river_06",
      "anchor_key": "mountain_west_river",
      "label": "Mountain West trout river, summer positioning month 6",
      "month": 6,
      "local_date": "2025-06-18",
      "state_code": "CO",
      "timezone": "America/Denver",
      "latitude": 38.4783,
      "longitude": -107.8762,
      "context": "freshwater_river",
      "region_key": "mountain_west",
      "default_clarity": "clear",
      "matrix_role": "core_monthly",
      "focus_window": "summer_positioning"
    },
    {
      "id": "trout_matrix_mountain_west_river_07",
      "anchor_key": "mountain_west_river",
      "label": "Mountain West trout river, summer positioning month 7",
      "month": 7,
      "local_date": "2025-07-16",
      "state_code": "CO",
      "timezone": "America/Denver",
      "latitude": 38.4783,
      "longitude": -107.8762,
      "context": "freshwater_river",
      "region_key": "mountain_west",
      "default_clarity": "clear",
      "matrix_role": "core_monthly",
      "focus_window": "summer_positioning"
    },
    {
      "id": "trout_matrix_mountain_west_river_08",
      "anchor_key": "mountain_west_river",
      "label": "Mountain West trout river, summer positioning month 8",
      "month": 8,
      "local_date": "2025-08-14",
      "state_code": "CO",
      "timezone": "America/Denver",
      "latitude": 38.4783,
      "longitude": -107.8762,
      "context": "freshwater_river",
      "region_key": "mountain_west",
      "default_clarity": "clear",
      "matrix_role": "core_monthly",
      "focus_window": "summer_positioning"
    },
    {
      "id": "trout_matrix_mountain_west_river_09",
      "anchor_key": "mountain_west_river",
      "label": "Mountain West trout river, fall transition month 9",
      "month": 9,
      "local_date": "2025-09-17",
      "state_code": "CO",
      "timezone": "America/Denver",
      "latitude": 38.4783,
      "longitude": -107.8762,
      "context": "freshwater_river",
      "region_key": "mountain_west",
      "default_clarity": "clear",
      "matrix_role": "core_monthly",
      "focus_window": "fall_transition"
    },
    {
      "id": "trout_matrix_mountain_west_river_10",
      "anchor_key": "mountain_west_river",
      "label": "Mountain West trout river, fall transition month 10",
      "month": 10,
      "local_date": "2025-10-15",
      "state_code": "CO",
      "timezone": "America/Denver",
      "latitude": 38.4783,
      "longitude": -107.8762,
      "context": "freshwater_river",
      "region_key": "mountain_west",
      "default_clarity": "clear",
      "matrix_role": "core_monthly",
      "focus_window": "fall_transition"
    },
    {
      "id": "trout_matrix_mountain_west_river_11",
      "anchor_key": "mountain_west_river",
      "label": "Mountain West trout river, fall transition month 11",
      "month": 11,
      "local_date": "2025-11-12",
      "state_code": "CO",
      "timezone": "America/Denver",
      "latitude": 38.4783,
      "longitude": -107.8762,
      "context": "freshwater_river",
      "region_key": "mountain_west",
      "default_clarity": "clear",
      "matrix_role": "core_monthly",
      "focus_window": "fall_transition"
    },
    {
      "id": "trout_matrix_mountain_west_river_12",
      "anchor_key": "mountain_west_river",
      "label": "Mountain West trout river, winter control month 12",
      "month": 12,
      "local_date": "2025-12-10",
      "state_code": "CO",
      "timezone": "America/Denver",
      "latitude": 38.4783,
      "longitude": -107.8762,
      "context": "freshwater_river",
      "region_key": "mountain_west",
      "default_clarity": "clear",
      "matrix_role": "core_monthly",
      "focus_window": "winter_control"
    },
    {
      "id": "trout_matrix_pacific_northwest_river_01",
      "anchor_key": "pacific_northwest_river",
      "label": "Pacific Northwest trout river, winter control month 1",
      "month": 1,
      "local_date": "2025-01-16",
      "state_code": "OR",
      "timezone": "America/Los_Angeles",
      "latitude": 44.3539,
      "longitude": -121.5498,
      "context": "freshwater_river",
      "region_key": "pacific_northwest",
      "default_clarity": "clear",
      "matrix_role": "core_monthly",
      "focus_window": "winter_control"
    },
    {
      "id": "trout_matrix_pacific_northwest_river_02",
      "anchor_key": "pacific_northwest_river",
      "label": "Pacific Northwest trout river, prespawn opening month 2",
      "month": 2,
      "local_date": "2025-02-19",
      "state_code": "OR",
      "timezone": "America/Los_Angeles",
      "latitude": 44.3539,
      "longitude": -121.5498,
      "context": "freshwater_river",
      "region_key": "pacific_northwest",
      "default_clarity": "clear",
      "matrix_role": "core_monthly",
      "focus_window": "prespawn_opening"
    },
    {
      "id": "trout_matrix_pacific_northwest_river_03",
      "anchor_key": "pacific_northwest_river",
      "label": "Pacific Northwest trout river, prespawn opening month 3",
      "month": 3,
      "local_date": "2025-03-20",
      "state_code": "OR",
      "timezone": "America/Los_Angeles",
      "latitude": 44.3539,
      "longitude": -121.5498,
      "context": "freshwater_river",
      "region_key": "pacific_northwest",
      "default_clarity": "clear",
      "matrix_role": "core_monthly",
      "focus_window": "prespawn_opening"
    },
    {
      "id": "trout_matrix_pacific_northwest_river_04",
      "anchor_key": "pacific_northwest_river",
      "label": "Pacific Northwest trout river, spawn postspawn transition month 4",
      "month": 4,
      "local_date": "2025-04-16",
      "state_code": "OR",
      "timezone": "America/Los_Angeles",
      "latitude": 44.3539,
      "longitude": -121.5498,
      "context": "freshwater_river",
      "region_key": "pacific_northwest",
      "default_clarity": "clear",
      "matrix_role": "core_monthly",
      "focus_window": "spawn_postspawn_transition"
    },
    {
      "id": "trout_matrix_pacific_northwest_river_05",
      "anchor_key": "pacific_northwest_river",
      "label": "Pacific Northwest trout river, spawn postspawn transition month 5",
      "month": 5,
      "local_date": "2025-05-15",
      "state_code": "OR",
      "timezone": "America/Los_Angeles",
      "latitude": 44.3539,
      "longitude": -121.5498,
      "context": "freshwater_river",
      "region_key": "pacific_northwest",
      "default_clarity": "clear",
      "matrix_role": "core_monthly",
      "focus_window": "spawn_postspawn_transition"
    },
    {
      "id": "trout_matrix_pacific_northwest_river_06",
      "anchor_key": "pacific_northwest_river",
      "label": "Pacific Northwest trout river, summer positioning month 6",
      "month": 6,
      "local_date": "2025-06-18",
      "state_code": "OR",
      "timezone": "America/Los_Angeles",
      "latitude": 44.3539,
      "longitude": -121.5498,
      "context": "freshwater_river",
      "region_key": "pacific_northwest",
      "default_clarity": "clear",
      "matrix_role": "core_monthly",
      "focus_window": "summer_positioning"
    },
    {
      "id": "trout_matrix_pacific_northwest_river_07",
      "anchor_key": "pacific_northwest_river",
      "label": "Pacific Northwest trout river, summer positioning month 7",
      "month": 7,
      "local_date": "2025-07-16",
      "state_code": "OR",
      "timezone": "America/Los_Angeles",
      "latitude": 44.3539,
      "longitude": -121.5498,
      "context": "freshwater_river",
      "region_key": "pacific_northwest",
      "default_clarity": "clear",
      "matrix_role": "core_monthly",
      "focus_window": "summer_positioning"
    },
    {
      "id": "trout_matrix_pacific_northwest_river_08",
      "anchor_key": "pacific_northwest_river",
      "label": "Pacific Northwest trout river, summer positioning month 8",
      "month": 8,
      "local_date": "2025-08-14",
      "state_code": "OR",
      "timezone": "America/Los_Angeles",
      "latitude": 44.3539,
      "longitude": -121.5498,
      "context": "freshwater_river",
      "region_key": "pacific_northwest",
      "default_clarity": "clear",
      "matrix_role": "core_monthly",
      "focus_window": "summer_positioning"
    },
    {
      "id": "trout_matrix_pacific_northwest_river_09",
      "anchor_key": "pacific_northwest_river",
      "label": "Pacific Northwest trout river, fall transition month 9",
      "month": 9,
      "local_date": "2025-09-17",
      "state_code": "OR",
      "timezone": "America/Los_Angeles",
      "latitude": 44.3539,
      "longitude": -121.5498,
      "context": "freshwater_river",
      "region_key": "pacific_northwest",
      "default_clarity": "clear",
      "matrix_role": "core_monthly",
      "focus_window": "fall_transition"
    },
    {
      "id": "trout_matrix_pacific_northwest_river_10",
      "anchor_key": "pacific_northwest_river",
      "label": "Pacific Northwest trout river, fall transition month 10",
      "month": 10,
      "local_date": "2025-10-15",
      "state_code": "OR",
      "timezone": "America/Los_Angeles",
      "latitude": 44.3539,
      "longitude": -121.5498,
      "context": "freshwater_river",
      "region_key": "pacific_northwest",
      "default_clarity": "clear",
      "matrix_role": "core_monthly",
      "focus_window": "fall_transition"
    },
    {
      "id": "trout_matrix_pacific_northwest_river_11",
      "anchor_key": "pacific_northwest_river",
      "label": "Pacific Northwest trout river, fall transition month 11",
      "month": 11,
      "local_date": "2025-11-12",
      "state_code": "OR",
      "timezone": "America/Los_Angeles",
      "latitude": 44.3539,
      "longitude": -121.5498,
      "context": "freshwater_river",
      "region_key": "pacific_northwest",
      "default_clarity": "clear",
      "matrix_role": "core_monthly",
      "focus_window": "fall_transition"
    },
    {
      "id": "trout_matrix_pacific_northwest_river_12",
      "anchor_key": "pacific_northwest_river",
      "label": "Pacific Northwest trout river, winter control month 12",
      "month": 12,
      "local_date": "2025-12-10",
      "state_code": "OR",
      "timezone": "America/Los_Angeles",
      "latitude": 44.3539,
      "longitude": -121.5498,
      "context": "freshwater_river",
      "region_key": "pacific_northwest",
      "default_clarity": "clear",
      "matrix_role": "core_monthly",
      "focus_window": "winter_control"
    },
    {
      "id": "trout_matrix_northern_california_fall_02",
      "anchor_key": "northern_california_fall",
      "label": "Northern California trout river, prespawn opening month 2",
      "month": 2,
      "local_date": "2025-02-19",
      "state_code": "CA",
      "timezone": "America/Los_Angeles",
      "latitude": 41.7922,
      "longitude": -122.6217,
      "context": "freshwater_river",
      "region_key": "northern_california",
      "default_clarity": "clear",
      "matrix_role": "seasonal_overlay",
      "focus_window": "prespawn_opening"
    },
    {
      "id": "trout_matrix_northern_california_fall_09",
      "anchor_key": "northern_california_fall",
      "label": "Northern California trout river, fall transition month 9",
      "month": 9,
      "local_date": "2025-09-17",
      "state_code": "CA",
      "timezone": "America/Los_Angeles",
      "latitude": 41.7922,
      "longitude": -122.6217,
      "context": "freshwater_river",
      "region_key": "northern_california",
      "default_clarity": "clear",
      "matrix_role": "seasonal_overlay",
      "focus_window": "fall_transition"
    },
    {
      "id": "trout_matrix_northern_california_fall_10",
      "anchor_key": "northern_california_fall",
      "label": "Northern California trout river, fall transition month 10",
      "month": 10,
      "local_date": "2025-10-15",
      "state_code": "CA",
      "timezone": "America/Los_Angeles",
      "latitude": 41.7922,
      "longitude": -122.6217,
      "context": "freshwater_river",
      "region_key": "northern_california",
      "default_clarity": "clear",
      "matrix_role": "seasonal_overlay",
      "focus_window": "fall_transition"
    },
    {
      "id": "trout_matrix_northern_california_fall_11",
      "anchor_key": "northern_california_fall",
      "label": "Northern California trout river, fall transition month 11",
      "month": 11,
      "local_date": "2025-11-12",
      "state_code": "CA",
      "timezone": "America/Los_Angeles",
      "latitude": 41.7922,
      "longitude": -122.6217,
      "context": "freshwater_river",
      "region_key": "northern_california",
      "default_clarity": "clear",
      "matrix_role": "seasonal_overlay",
      "focus_window": "fall_transition"
    },
    {
      "id": "trout_matrix_great_lakes_highwater_03",
      "anchor_key": "great_lakes_highwater",
      "label": "Great Lakes / Upper Midwest trout river, prespawn opening month 3",
      "month": 3,
      "local_date": "2025-03-20",
      "state_code": "WI",
      "timezone": "America/Chicago",
      "latitude": 46.0042,
      "longitude": -89.6651,
      "context": "freshwater_river",
      "region_key": "great_lakes_upper_midwest",
      "default_clarity": "stained",
      "matrix_role": "seasonal_overlay",
      "focus_window": "prespawn_opening"
    },
    {
      "id": "trout_matrix_great_lakes_highwater_05",
      "anchor_key": "great_lakes_highwater",
      "label": "Great Lakes / Upper Midwest trout river, spawn postspawn transition month 5",
      "month": 5,
      "local_date": "2025-05-15",
      "state_code": "WI",
      "timezone": "America/Chicago",
      "latitude": 46.0042,
      "longitude": -89.6651,
      "context": "freshwater_river",
      "region_key": "great_lakes_upper_midwest",
      "default_clarity": "stained",
      "matrix_role": "seasonal_overlay",
      "focus_window": "spawn_postspawn_transition"
    },
    {
      "id": "trout_matrix_great_lakes_highwater_10",
      "anchor_key": "great_lakes_highwater",
      "label": "Great Lakes / Upper Midwest trout river, fall transition month 10",
      "month": 10,
      "local_date": "2025-10-15",
      "state_code": "WI",
      "timezone": "America/Chicago",
      "latitude": 46.0042,
      "longitude": -89.6651,
      "context": "freshwater_river",
      "region_key": "great_lakes_upper_midwest",
      "default_clarity": "stained",
      "matrix_role": "seasonal_overlay",
      "focus_window": "fall_transition"
    },
    {
      "id": "trout_matrix_great_lakes_highwater_11",
      "anchor_key": "great_lakes_highwater",
      "label": "Great Lakes / Upper Midwest trout river, fall transition month 11",
      "month": 11,
      "local_date": "2025-11-12",
      "state_code": "WI",
      "timezone": "America/Chicago",
      "latitude": 46.0042,
      "longitude": -89.6651,
      "context": "freshwater_river",
      "region_key": "great_lakes_upper_midwest",
      "default_clarity": "stained",
      "matrix_role": "seasonal_overlay",
      "focus_window": "fall_transition"
    },
    {
      "id": "trout_matrix_alaska_big_river_06",
      "anchor_key": "alaska_big_river",
      "label": "Alaska trout river, summer positioning month 6",
      "month": 6,
      "local_date": "2025-06-18",
      "state_code": "AK",
      "timezone": "America/Anchorage",
      "latitude": 61.5799,
      "longitude": -149.4411,
      "context": "freshwater_river",
      "region_key": "alaska",
      "default_clarity": "clear",
      "matrix_role": "seasonal_overlay",
      "focus_window": "summer_positioning"
    },
    {
      "id": "trout_matrix_alaska_big_river_09",
      "anchor_key": "alaska_big_river",
      "label": "Alaska trout river, fall transition month 9",
      "month": 9,
      "local_date": "2025-09-17",
      "state_code": "AK",
      "timezone": "America/Anchorage",
      "latitude": 61.5799,
      "longitude": -149.4411,
      "context": "freshwater_river",
      "region_key": "alaska",
      "default_clarity": "clear",
      "matrix_role": "seasonal_overlay",
      "focus_window": "fall_transition"
    },
    {
      "id": "trout_matrix_alaska_big_river_11",
      "anchor_key": "alaska_big_river",
      "label": "Alaska trout river, fall transition month 11",
      "month": 11,
      "local_date": "2025-11-12",
      "state_code": "AK",
      "timezone": "America/Anchorage",
      "latitude": 61.5799,
      "longitude": -149.4411,
      "context": "freshwater_river",
      "region_key": "alaska",
      "default_clarity": "clear",
      "matrix_role": "seasonal_overlay",
      "focus_window": "fall_transition"
    },
    {
      "id": "trout_matrix_alaska_big_river_12",
      "anchor_key": "alaska_big_river",
      "label": "Alaska trout river, winter control month 12",
      "month": 12,
      "local_date": "2025-12-10",
      "state_code": "AK",
      "timezone": "America/Anchorage",
      "latitude": 61.5799,
      "longitude": -149.4411,
      "context": "freshwater_river",
      "region_key": "alaska",
      "default_clarity": "clear",
      "matrix_role": "seasonal_overlay",
      "focus_window": "winter_control"
    },
    {
      "id": "trout_matrix_idaho_runoff_edge_04",
      "anchor_key": "idaho_runoff_edge",
      "label": "Idaho runoff-edge trout river, spawn postspawn transition month 4",
      "month": 4,
      "local_date": "2025-04-16",
      "state_code": "ID",
      "timezone": "America/Boise",
      "latitude": 44.0772,
      "longitude": -114.742,
      "context": "freshwater_river",
      "region_key": "mountain_west",
      "default_clarity": "stained",
      "matrix_role": "seasonal_overlay",
      "focus_window": "spawn_postspawn_transition"
    },
    {
      "id": "trout_matrix_idaho_runoff_edge_06",
      "anchor_key": "idaho_runoff_edge",
      "label": "Idaho runoff-edge trout river, summer positioning month 6",
      "month": 6,
      "local_date": "2025-06-18",
      "state_code": "ID",
      "timezone": "America/Boise",
      "latitude": 44.0772,
      "longitude": -114.742,
      "context": "freshwater_river",
      "region_key": "mountain_west",
      "default_clarity": "stained",
      "matrix_role": "seasonal_overlay",
      "focus_window": "summer_positioning"
    },
    {
      "id": "trout_matrix_idaho_runoff_edge_07",
      "anchor_key": "idaho_runoff_edge",
      "label": "Idaho runoff-edge trout river, summer positioning month 7",
      "month": 7,
      "local_date": "2025-07-16",
      "state_code": "ID",
      "timezone": "America/Boise",
      "latitude": 44.0772,
      "longitude": -114.742,
      "context": "freshwater_river",
      "region_key": "mountain_west",
      "default_clarity": "stained",
      "matrix_role": "seasonal_overlay",
      "focus_window": "summer_positioning"
    },
    {
      "id": "trout_matrix_idaho_runoff_edge_08",
      "anchor_key": "idaho_runoff_edge",
      "label": "Idaho runoff-edge trout river, summer positioning month 8",
      "month": 8,
      "local_date": "2025-08-14",
      "state_code": "ID",
      "timezone": "America/Boise",
      "latitude": 44.0772,
      "longitude": -114.742,
      "context": "freshwater_river",
      "region_key": "mountain_west",
      "default_clarity": "stained",
      "matrix_role": "seasonal_overlay",
      "focus_window": "summer_positioning"
    },
    {
      "id": "trout_matrix_south_central_tailwater_04",
      "anchor_key": "south_central_tailwater",
      "label": "South-central tailwater trout river, spawn postspawn transition month 4",
      "month": 4,
      "local_date": "2025-04-16",
      "state_code": "TN",
      "timezone": "America/New_York",
      "latitude": 35.4409,
      "longitude": -84.6013,
      "context": "freshwater_river",
      "region_key": "south_central",
      "default_clarity": "stained",
      "matrix_role": "seasonal_overlay",
      "focus_window": "spawn_postspawn_transition"
    },
    {
      "id": "trout_matrix_south_central_tailwater_06",
      "anchor_key": "south_central_tailwater",
      "label": "South-central tailwater trout river, summer positioning month 6",
      "month": 6,
      "local_date": "2025-06-18",
      "state_code": "TN",
      "timezone": "America/New_York",
      "latitude": 35.4409,
      "longitude": -84.6013,
      "context": "freshwater_river",
      "region_key": "south_central",
      "default_clarity": "stained",
      "matrix_role": "seasonal_overlay",
      "focus_window": "summer_positioning"
    },
    {
      "id": "trout_matrix_south_central_tailwater_07",
      "anchor_key": "south_central_tailwater",
      "label": "South-central tailwater trout river, summer positioning month 7",
      "month": 7,
      "local_date": "2025-07-16",
      "state_code": "TN",
      "timezone": "America/New_York",
      "latitude": 35.4409,
      "longitude": -84.6013,
      "context": "freshwater_river",
      "region_key": "south_central",
      "default_clarity": "stained",
      "matrix_role": "seasonal_overlay",
      "focus_window": "summer_positioning"
    },
    {
      "id": "trout_matrix_south_central_tailwater_08",
      "anchor_key": "south_central_tailwater",
      "label": "South-central tailwater trout river, summer positioning month 8",
      "month": 8,
      "local_date": "2025-08-14",
      "state_code": "TN",
      "timezone": "America/New_York",
      "latitude": 35.4409,
      "longitude": -84.6013,
      "context": "freshwater_river",
      "region_key": "south_central",
      "default_clarity": "stained",
      "matrix_role": "seasonal_overlay",
      "focus_window": "summer_positioning"
    }
  ]
}
