{
  "generated_at": "2026-04-10T13:18:20.405Z",
  "audited_rows": 1104,
  "synthetic_daily_states_per_row": 648,
  "lure": {
    "states": 2146176,
    "top1_changed_vs_neutral_ratio": 0.1671,
    "top3_changed_vs_neutral_ratio": 0.3456,
    "components": {
      "seasonal_baseline": {
        "winner_mean": 10.0562,
        "winner_abs_mean": 10.0562,
        "decisive_share": 0.8562,
        "mean_decisive_margin": 1.6169,
        "max_decisive_margin": 3
      },
      "daily_modifier": {
        "winner_mean": 2.3518,
        "winner_abs_mean": 2.3518,
        "decisive_share": 0.0241,
        "mean_decisive_margin": 0.8089,
        "max_decisive_margin": 1.35
      },
      "clarity_modifier": {
        "winner_mean": 0,
        "winner_abs_mean": 0,
        "decisive_share": 0,
        "mean_decisive_margin": 0,
        "max_decisive_margin": 0
      },
      "forage_bonus": {
        "winner_mean": 1.4334,
        "winner_abs_mean": 1.4334,
        "decisive_share": 0.0203,
        "mean_decisive_margin": 0.767,
        "max_decisive_margin": 1.5
      },
      "lane_window_bonus": {
        "winner_mean": 0.0667,
        "winner_abs_mean": 0.1088,
        "decisive_share": 0.0436,
        "mean_decisive_margin": 0.9471,
        "max_decisive_margin": 1.25
      },
      "tactical_window_bonus": {
        "winner_mean": 0.2348,
        "winner_abs_mean": 0.338,
        "decisive_share": 0.0536,
        "mean_decisive_margin": 1.1377,
        "max_decisive_margin": 1.45
      },
      "pace_bias_bonus": {
        "winner_mean": 0.11,
        "winner_abs_mean": 0.2149,
        "decisive_share": 0.0022,
        "mean_decisive_margin": 0.3182,
        "max_decisive_margin": 0.5
      }
    },
    "groups": {
      "seasonal_core": {
        "decisive_share": 0.8786,
        "mean_decisive_margin": 1.5844,
        "max_decisive_margin": 3
      },
      "daily_stack": {
        "decisive_share": 0.1052,
        "mean_decisive_margin": 1.1805,
        "max_decisive_margin": 3.05
      },
      "forage": {
        "decisive_share": 0.0162,
        "mean_decisive_margin": 0.8272,
        "max_decisive_margin": 1.5
      },
      "clarity": {
        "decisive_share": 0,
        "mean_decisive_margin": 0,
        "max_decisive_margin": 0
      }
    }
  },
  "fly": {
    "states": 2146176,
    "top1_changed_vs_neutral_ratio": 0.1632,
    "top3_changed_vs_neutral_ratio": 0.4636,
    "components": {
      "seasonal_baseline": {
        "winner_mean": 9.9737,
        "winner_abs_mean": 9.9737,
        "decisive_share": 0.8846,
        "mean_decisive_margin": 1.7345,
        "max_decisive_margin": 3.3
      },
      "daily_modifier": {
        "winner_mean": 2.2152,
        "winner_abs_mean": 2.2152,
        "decisive_share": 0.0232,
        "mean_decisive_margin": 0.9943,
        "max_decisive_margin": 2.55
      },
      "clarity_modifier": {
        "winner_mean": 0,
        "winner_abs_mean": 0,
        "decisive_share": 0,
        "mean_decisive_margin": 0,
        "max_decisive_margin": 0
      },
      "forage_bonus": {
        "winner_mean": 1.4674,
        "winner_abs_mean": 1.4674,
        "decisive_share": 0.0003,
        "mean_decisive_margin": 0.5,
        "max_decisive_margin": 0.5
      },
      "lane_window_bonus": {
        "winner_mean": 0.0348,
        "winner_abs_mean": 0.1365,
        "decisive_share": 0.0445,
        "mean_decisive_margin": 1.165,
        "max_decisive_margin": 1.6
      },
      "tactical_window_bonus": {
        "winner_mean": 0.1755,
        "winner_abs_mean": 0.3178,
        "decisive_share": 0.0248,
        "mean_decisive_margin": 1.2105,
        "max_decisive_margin": 1.25
      },
      "pace_bias_bonus": {
        "winner_mean": 0.1493,
        "winner_abs_mean": 0.2322,
        "decisive_share": 0.0225,
        "mean_decisive_margin": 0.575,
        "max_decisive_margin": 0.7
      }
    },
    "groups": {
      "seasonal_core": {
        "decisive_share": 0.8566,
        "mean_decisive_margin": 1.733,
        "max_decisive_margin": 3.3
      },
      "daily_stack": {
        "decisive_share": 0.142,
        "mean_decisive_margin": 1.4163,
        "max_decisive_margin": 4.5
      },
      "forage": {
        "decisive_share": 0.0013,
        "mean_decisive_margin": 0.5,
        "max_decisive_margin": 0.5
      },
      "clarity": {
        "decisive_share": 0,
        "mean_decisive_margin": 0,
        "max_decisive_margin": 0
      }
    }
  },
  "examples": {
    "lure": [
      {
        "species": "largemouth_bass",
        "region_key": "florida",
        "month": 1,
        "context": "freshwater_lake_pond",
        "clarity": "clear",
        "top1": "texas_rigged_soft_plastic_craw",
        "runner_up": "suspending_jerkbait",
        "decisive_component": "seasonal_baseline",
        "decisive_margin": 1.1,
        "decisive_group": "seasonal_core",
        "group_margin": 1.1
      },
      {
        "species": "largemouth_bass",
        "region_key": "florida",
        "month": 1,
        "context": "freshwater_lake_pond",
        "clarity": "clear",
        "top1": "texas_rigged_soft_plastic_craw",
        "runner_up": "suspending_jerkbait",
        "decisive_component": "seasonal_baseline",
        "decisive_margin": 1.1,
        "decisive_group": "seasonal_core",
        "group_margin": 1.1
      },
      {
        "species": "largemouth_bass",
        "region_key": "florida",
        "month": 1,
        "context": "freshwater_lake_pond",
        "clarity": "clear",
        "top1": "suspending_jerkbait",
        "runner_up": "texas_rigged_soft_plastic_craw",
        "decisive_component": "tactical_window_bonus",
        "decisive_margin": 1.15,
        "decisive_group": "daily_stack",
        "group_margin": 1.05
      },
      {
        "species": "largemouth_bass",
        "region_key": "florida",
        "month": 1,
        "context": "freshwater_lake_pond",
        "clarity": "clear",
        "top1": "texas_rigged_soft_plastic_craw",
        "runner_up": "football_jig",
        "decisive_component": "seasonal_baseline",
        "decisive_margin": 2.6,
        "decisive_group": "seasonal_core",
        "group_margin": 2.6
      },
      {
        "species": "largemouth_bass",
        "region_key": "florida",
        "month": 1,
        "context": "freshwater_lake_pond",
        "clarity": "clear",
        "top1": "texas_rigged_soft_plastic_craw",
        "runner_up": "football_jig",
        "decisive_component": "seasonal_baseline",
        "decisive_margin": 2.6,
        "decisive_group": "seasonal_core",
        "group_margin": 2.6
      },
      {
        "species": "largemouth_bass",
        "region_key": "florida",
        "month": 1,
        "context": "freshwater_lake_pond",
        "clarity": "clear",
        "top1": "texas_rigged_soft_plastic_craw",
        "runner_up": "suspending_jerkbait",
        "decisive_component": "seasonal_baseline",
        "decisive_margin": 1.1,
        "decisive_group": "seasonal_core",
        "group_margin": 1.1
      },
      {
        "species": "largemouth_bass",
        "region_key": "florida",
        "month": 1,
        "context": "freshwater_lake_pond",
        "clarity": "clear",
        "top1": "texas_rigged_soft_plastic_craw",
        "runner_up": "suspending_jerkbait",
        "decisive_component": "seasonal_baseline",
        "decisive_margin": 1.1,
        "decisive_group": "seasonal_core",
        "group_margin": 1.1
      },
      {
        "species": "largemouth_bass",
        "region_key": "florida",
        "month": 1,
        "context": "freshwater_lake_pond",
        "clarity": "clear",
        "top1": "texas_rigged_soft_plastic_craw",
        "runner_up": "suspending_jerkbait",
        "decisive_component": "seasonal_baseline",
        "decisive_margin": 1.1,
        "decisive_group": "seasonal_core",
        "group_margin": 1.1
      },
      {
        "species": "largemouth_bass",
        "region_key": "florida",
        "month": 1,
        "context": "freshwater_lake_pond",
        "clarity": "clear",
        "top1": "suspending_jerkbait",
        "runner_up": "texas_rigged_soft_plastic_craw",
        "decisive_component": "tactical_window_bonus",
        "decisive_margin": 1.15,
        "decisive_group": "daily_stack",
        "group_margin": 0.8
      },
      {
        "species": "largemouth_bass",
        "region_key": "florida",
        "month": 1,
        "context": "freshwater_lake_pond",
        "clarity": "clear",
        "top1": "texas_rigged_soft_plastic_craw",
        "runner_up": "football_jig",
        "decisive_component": "seasonal_baseline",
        "decisive_margin": 2.6,
        "decisive_group": "seasonal_core",
        "group_margin": 2.6
      },
      {
        "species": "largemouth_bass",
        "region_key": "florida",
        "month": 1,
        "context": "freshwater_lake_pond",
        "clarity": "clear",
        "top1": "texas_rigged_soft_plastic_craw",
        "runner_up": "football_jig",
        "decisive_component": "seasonal_baseline",
        "decisive_margin": 2.6,
        "decisive_group": "seasonal_core",
        "group_margin": 2.6
      },
      {
        "species": "largemouth_bass",
        "region_key": "florida",
        "month": 1,
        "context": "freshwater_lake_pond",
        "clarity": "clear",
        "top1": "texas_rigged_soft_plastic_craw",
        "runner_up": "suspending_jerkbait",
        "decisive_component": "seasonal_baseline",
        "decisive_margin": 1.1,
        "decisive_group": "seasonal_core",
        "group_margin": 1.1
      },
      {
        "species": "largemouth_bass",
        "region_key": "florida",
        "month": 1,
        "context": "freshwater_lake_pond",
        "clarity": "clear",
        "top1": "texas_rigged_soft_plastic_craw",
        "runner_up": "suspending_jerkbait",
        "decisive_component": "seasonal_baseline",
        "decisive_margin": 1.1,
        "decisive_group": "seasonal_core",
        "group_margin": 1.1
      },
      {
        "species": "largemouth_bass",
        "region_key": "florida",
        "month": 1,
        "context": "freshwater_lake_pond",
        "clarity": "clear",
        "top1": "texas_rigged_soft_plastic_craw",
        "runner_up": "suspending_jerkbait",
        "decisive_component": "seasonal_baseline",
        "decisive_margin": 1.1,
        "decisive_group": "seasonal_core",
        "group_margin": 1.1
      },
      {
        "species": "largemouth_bass",
        "region_key": "florida",
        "month": 1,
        "context": "freshwater_lake_pond",
        "clarity": "clear",
        "top1": "texas_rigged_soft_plastic_craw",
        "runner_up": "suspending_jerkbait",
        "decisive_component": "seasonal_baseline",
        "decisive_margin": 1.1,
        "decisive_group": "seasonal_core",
        "group_margin": 1.1
      },
      {
        "species": "largemouth_bass",
        "region_key": "florida",
        "month": 1,
        "context": "freshwater_lake_pond",
        "clarity": "clear",
        "top1": "texas_rigged_soft_plastic_craw",
        "runner_up": "football_jig",
        "decisive_component": "seasonal_baseline",
        "decisive_margin": 2.6,
        "decisive_group": "seasonal_core",
        "group_margin": 2.6
      },
      {
        "species": "largemouth_bass",
        "region_key": "florida",
        "month": 1,
        "context": "freshwater_lake_pond",
        "clarity": "clear",
        "top1": "texas_rigged_soft_plastic_craw",
        "runner_up": "football_jig",
        "decisive_component": "seasonal_baseline",
        "decisive_margin": 2.6,
        "decisive_group": "seasonal_core",
        "group_margin": 2.6
      },
      {
        "species": "largemouth_bass",
        "region_key": "florida",
        "month": 1,
        "context": "freshwater_lake_pond",
        "clarity": "clear",
        "top1": "texas_rigged_soft_plastic_craw",
        "runner_up": "suspending_jerkbait",
        "decisive_component": "seasonal_baseline",
        "decisive_margin": 1.1,
        "decisive_group": "seasonal_core",
        "group_margin": 1.1
      },
      {
        "species": "largemouth_bass",
        "region_key": "florida",
        "month": 1,
        "context": "freshwater_lake_pond",
        "clarity": "clear",
        "top1": "texas_rigged_soft_plastic_craw",
        "runner_up": "suspending_jerkbait",
        "decisive_component": "seasonal_baseline",
        "decisive_margin": 1.1,
        "decisive_group": "seasonal_core",
        "group_margin": 1.1
      },
      {
        "species": "largemouth_bass",
        "region_key": "florida",
        "month": 1,
        "context": "freshwater_lake_pond",
        "clarity": "clear",
        "top1": "texas_rigged_soft_plastic_craw",
        "runner_up": "suspending_jerkbait",
        "decisive_component": "seasonal_baseline",
        "decisive_margin": 1.1,
        "decisive_group": "seasonal_core",
        "group_margin": 1.1
      }
    ],
    "fly": [
      {
        "species": "largemouth_bass",
        "region_key": "florida",
        "month": 1,
        "context": "freshwater_lake_pond",
        "clarity": "clear",
        "top1": "crawfish_streamer",
        "runner_up": "clouser_minnow",
        "decisive_component": "seasonal_baseline",
        "decisive_margin": 2.95,
        "decisive_group": "seasonal_core",
        "group_margin": 2.95
      },
      {
        "species": "largemouth_bass",
        "region_key": "florida",
        "month": 1,
        "context": "freshwater_lake_pond",
        "clarity": "clear",
        "top1": "woolly_bugger",
        "runner_up": "clouser_minnow",
        "decisive_component": "seasonal_baseline",
        "decisive_margin": 2.2,
        "decisive_group": "seasonal_core",
        "group_margin": 2.2
      },
      {
        "species": "largemouth_bass",
        "region_key": "florida",
        "month": 1,
        "context": "freshwater_lake_pond",
        "clarity": "clear",
        "top1": "woolly_bugger",
        "runner_up": "clouser_minnow",
        "decisive_component": "seasonal_baseline",
        "decisive_margin": 2.2,
        "decisive_group": "seasonal_core",
        "group_margin": 2.2
      },
      {
        "species": "largemouth_bass",
        "region_key": "florida",
        "month": 1,
        "context": "freshwater_lake_pond",
        "clarity": "clear",
        "top1": "crawfish_streamer",
        "runner_up": "clouser_minnow",
        "decisive_component": "seasonal_baseline",
        "decisive_margin": 2.95,
        "decisive_group": "seasonal_core",
        "group_margin": 2.95
      },
      {
        "species": "largemouth_bass",
        "region_key": "florida",
        "month": 1,
        "context": "freshwater_lake_pond",
        "clarity": "clear",
        "top1": "crawfish_streamer",
        "runner_up": "clouser_minnow",
        "decisive_component": "seasonal_baseline",
        "decisive_margin": 2.95,
        "decisive_group": "seasonal_core",
        "group_margin": 2.95
      },
      {
        "species": "largemouth_bass",
        "region_key": "florida",
        "month": 1,
        "context": "freshwater_lake_pond",
        "clarity": "clear",
        "top1": "crawfish_streamer",
        "runner_up": "clouser_minnow",
        "decisive_component": "seasonal_baseline",
        "decisive_margin": 2.95,
        "decisive_group": "seasonal_core",
        "group_margin": 2.95
      },
      {
        "species": "largemouth_bass",
        "region_key": "florida",
        "month": 1,
        "context": "freshwater_lake_pond",
        "clarity": "clear",
        "top1": "crawfish_streamer",
        "runner_up": "clouser_minnow",
        "decisive_component": "seasonal_baseline",
        "decisive_margin": 2.95,
        "decisive_group": "seasonal_core",
        "group_margin": 2.95
      },
      {
        "species": "largemouth_bass",
        "region_key": "florida",
        "month": 1,
        "context": "freshwater_lake_pond",
        "clarity": "clear",
        "top1": "woolly_bugger",
        "runner_up": "clouser_minnow",
        "decisive_component": "seasonal_baseline",
        "decisive_margin": 2.2,
        "decisive_group": "seasonal_core",
        "group_margin": 2.2
      },
      {
        "species": "largemouth_bass",
        "region_key": "florida",
        "month": 1,
        "context": "freshwater_lake_pond",
        "clarity": "clear",
        "top1": "woolly_bugger",
        "runner_up": "clouser_minnow",
        "decisive_component": "seasonal_baseline",
        "decisive_margin": 2.2,
        "decisive_group": "seasonal_core",
        "group_margin": 2.2
      },
      {
        "species": "largemouth_bass",
        "region_key": "florida",
        "month": 1,
        "context": "freshwater_lake_pond",
        "clarity": "clear",
        "top1": "crawfish_streamer",
        "runner_up": "clouser_minnow",
        "decisive_component": "seasonal_baseline",
        "decisive_margin": 2.95,
        "decisive_group": "seasonal_core",
        "group_margin": 2.95
      },
      {
        "species": "largemouth_bass",
        "region_key": "florida",
        "month": 1,
        "context": "freshwater_lake_pond",
        "clarity": "clear",
        "top1": "crawfish_streamer",
        "runner_up": "clouser_minnow",
        "decisive_component": "seasonal_baseline",
        "decisive_margin": 2.95,
        "decisive_group": "seasonal_core",
        "group_margin": 2.95
      },
      {
        "species": "largemouth_bass",
        "region_key": "florida",
        "month": 1,
        "context": "freshwater_lake_pond",
        "clarity": "clear",
        "top1": "crawfish_streamer",
        "runner_up": "clouser_minnow",
        "decisive_component": "seasonal_baseline",
        "decisive_margin": 2.95,
        "decisive_group": "seasonal_core",
        "group_margin": 2.95
      },
      {
        "species": "largemouth_bass",
        "region_key": "florida",
        "month": 1,
        "context": "freshwater_lake_pond",
        "clarity": "clear",
        "top1": "crawfish_streamer",
        "runner_up": "clouser_minnow",
        "decisive_component": "seasonal_baseline",
        "decisive_margin": 2.95,
        "decisive_group": "seasonal_core",
        "group_margin": 2.95
      },
      {
        "species": "largemouth_bass",
        "region_key": "florida",
        "month": 1,
        "context": "freshwater_lake_pond",
        "clarity": "clear",
        "top1": "woolly_bugger",
        "runner_up": "clouser_minnow",
        "decisive_component": "seasonal_baseline",
        "decisive_margin": 2.2,
        "decisive_group": "seasonal_core",
        "group_margin": 2.2
      },
      {
        "species": "largemouth_bass",
        "region_key": "florida",
        "month": 1,
        "context": "freshwater_lake_pond",
        "clarity": "clear",
        "top1": "woolly_bugger",
        "runner_up": "clouser_minnow",
        "decisive_component": "seasonal_baseline",
        "decisive_margin": 2.2,
        "decisive_group": "seasonal_core",
        "group_margin": 2.2
      },
      {
        "species": "largemouth_bass",
        "region_key": "florida",
        "month": 1,
        "context": "freshwater_lake_pond",
        "clarity": "clear",
        "top1": "crawfish_streamer",
        "runner_up": "clouser_minnow",
        "decisive_component": "seasonal_baseline",
        "decisive_margin": 2.95,
        "decisive_group": "seasonal_core",
        "group_margin": 2.95
      },
      {
        "species": "largemouth_bass",
        "region_key": "florida",
        "month": 1,
        "context": "freshwater_lake_pond",
        "clarity": "clear",
        "top1": "crawfish_streamer",
        "runner_up": "clouser_minnow",
        "decisive_component": "seasonal_baseline",
        "decisive_margin": 2.95,
        "decisive_group": "seasonal_core",
        "group_margin": 2.95
      },
      {
        "species": "largemouth_bass",
        "region_key": "florida",
        "month": 1,
        "context": "freshwater_lake_pond",
        "clarity": "clear",
        "top1": "crawfish_streamer",
        "runner_up": "clouser_minnow",
        "decisive_component": "seasonal_baseline",
        "decisive_margin": 2.95,
        "decisive_group": "seasonal_core",
        "group_margin": 2.95
      },
      {
        "species": "largemouth_bass",
        "region_key": "florida",
        "month": 1,
        "context": "freshwater_lake_pond",
        "clarity": "clear",
        "top1": "crawfish_streamer",
        "runner_up": "clouser_minnow",
        "decisive_component": "seasonal_baseline",
        "decisive_margin": 2.95,
        "decisive_group": "seasonal_core",
        "group_margin": 2.95
      },
      {
        "species": "largemouth_bass",
        "region_key": "florida",
        "month": 1,
        "context": "freshwater_lake_pond",
        "clarity": "clear",
        "top1": "woolly_bugger",
        "runner_up": "clouser_minnow",
        "decisive_component": "seasonal_baseline",
        "decisive_margin": 2.2,
        "decisive_group": "seasonal_core",
        "group_margin": 2.2
      }
    ]
  }
}